Workbook

Sheet Read me
A1: Competitor tender master: edge, road and rail cost
A2: EDGE RULE (yours): VWLR has a PFT siding with 3 rail lines. A tender is an edge only if the MINE or the PLANT is within 150 km of VWLR. Everything else is context on rivals.
A3: Edge = Yes (an end within 150 km straight-line) | Borderline (150-180 km, about 150 km by road) | No (known ends all far) | Unknown (an end could not be identified from the title).
A4: Locations: mine and plant are matched from the tender title to the nearest listed town. Town coordinates were geocoded on 2026-10-12; the exact mine site is approximate [UNVERIFIED]. Reference point is Raigarh town until you name your siding's railway station (Settings).
A5: Costs per tonne: ROAD = near-end km x road factor x your road rate (+GST, +handling). RAIL = FOIS class 145A base tariff for the far-end km when that end is known, plus GST. FOIS excludes surcharges and siding charges. No tonnage is in the export, so no per-contract figures.
A6: Winner's own cost is unknown: this sheet shows where freight could have been your lever, not who would have won.
A7: Yellow cells are inputs. Everything else is a formula.

Sheet Master
A1: Edge | B1: Basis | C1: Mine (matched) | D1: Mine km | E1: Plant / siding (matched) | F1: Plant km | G1: Nearest end km | H1: TR247 ID | I1: Tender ref | J1: Title | K1: Category | L1: Buyer | M1: State | N1: Tender city | O1: Close date | P1: Stage | Q1: Winner | R1: Tracked rivals bidding | S1: Bidders | T1: Contract Rs Cr | U1: Road leg Rs/t (near end to your siding) | V1: Far-end km | W1: Rail leg Rs/t (your siding to far end, FOIS 145A) | X1: Indicative total Rs/t | Y1: Rate status
A2: Yes | B2: mine = coal company's tender city; siding = same area | C2: Raigarh (tender city) | D2: 0 | E2: Raigarh (tender city) | F2: 0 | G2: 0 | H2: 16341071 | I2: GEM/2025/B/7003513 | J2: handling service, hiring of pay loaders incorporatedfitted with weight sensors for mechanical transfer of crushed coal below100mm in to railway wagons all around the width of b.. | K2: Loading / handling / crushing | L2: South Eastern Coalfields Limited | M2: Chhattisgarh | N2: Raigarh | O2: 46022 | P2: AOC | Q2: G K Associates | R2: G K Associates, Chandan Kumar Singh | S2: 4 named / 4 | T2: 5.39 | U2: =IF(ISNUMBER(G2),MAX(MAX(G2,Settings!$B$13)*Settings!$B$7*Settings!$B$5,IF(ISNUMBER(Settings!$B$12),Settings!$B$12,0))*(1+IF(Settings!$B$11="Y",0,Settings!$B$10/100))+N(Settings!$B$9),"") | W2: =IF(ISNUMBER(V2),IF(V2*Settings!$B$8>1000,"beyond table",IFERROR(LOOKUP(V2*Settings!$B$8,'FOIS 145A'!$A$2:$A$22,'FOIS 145A'!$C$2:$C$22)*(1+IF(Settings!$B$11="Y",0,Settings!$B$10/100)),"")),"") | X2: =IF(AND(ISNUMBER(U2),ISNUMBER(W2)),U2+W2,"") | Y2: =Settings!$B$6
A3: Yes | B3: mine = coal company's tender city; siding = same area | C3: Raigarh (tender city) | D3: 0 | E3: Raigarh (tender city) | F3: 0 | G3: 0 | H3: 15858739 | I3: GEM/2025/B/6353919 | J3: handling ,transport and other mining services - percentagequote based - handling & transport service, ob removal,coal extraction, composite work ob removal, loading andtransportation of coal , extract | K3: Mining services (OB / extraction) | L3: South Eastern Coalfields Limited | M3: Chhattisgarh | N3: Raigarh | O3: 45885 | P3: AOC | Q3: Sical Logistics Limited | R3: Caliber Mining and Logistics | S3: 5 named / 25 | T3: 4038.18 | U3: =IF(ISNUMBER(G3),MAX(MAX(G3,Settings!$B$13)*Settings!$B$7*Settings!$B$5,IF(ISNUMBER(Settings!$B$12),Settings!$B$12,0))*(1+IF(Settings!$B$11="Y",0,Settings!$B$10/100))+N(Settings!$B$9),"") | W3: =IF(ISNUMBER(V3),IF(V3*Settings!$B$8>1000,"beyond table",IFERROR(LOOKUP(V3*Settings!$B$8,'FOIS 145A'!$A$2:$A$22,'FOIS 145A'!$C$2:$C$22)*(1+IF(Settings!$B$11="Y",0,Settings!$B$10/100)),"")),"") | X3: =IF(AND(ISNUMBER(U3),ISNUMBER(W3)),U3+W3,"") | Y3: =Settings!$B$6
A4: Yes | B4: plant = tender city | E4: Sundargarh district (IB Valley / Hemgir) (tender city) | F4: 32 | G4: 32 | H4: 14060255 | I4: GEM/2025/B/6194484 | J4: domestic coal for ntpc | K4: Coal supply | L4: National Thermal Power Corporation Limited | M4: Orissa | N4: Sundergarh | O4: 45817 | P4: Financial | Q4: - | R4: Godavari Commodities, Sendoz Impex | S4: 3 named / 3 | U4: =IF(ISNUMBER(G4),MAX(MAX(G4,Settings!$B$13)*Settings!$B$7*Settings!$B$5,IF(ISNUMBER(Settings!$B$12),Settings!$B$12,0))*(1+IF(Settings!$B$11="Y",0,Settings!$B$10/100))+N(Settings!$B$9),"") | W4: =IF(ISNUMBER(V4),IF(V4*Settings!$B$8>1000,"beyond table",IFERROR(LOOKUP(V4*Settings!$B$8,'FOIS 145A'!$A$2:$A$22,'FOIS 145A'!$C$2:$C$22)*(1+IF(Settings!$B$11="Y",0,Settings!$B$10/100)),"")),"") | X4: =IF(AND(ISNUMBER(U4),ISNUMBER(W4)),U4+W4,"") | Y4: =Settings!$B$6
A5: Yes | B5: mine named in title; plant/siding named in title | C5: Hemgir / Manoharpur (Sundargarh) | D5: 32 | E5: Rourkela | F5: 156 | G5: 32 | H5: 17865617 | I5: GEM/2026/B/7514337 | J5: transportation of coal from ocpl manoharpur mines to any privatepublic siding of railways and then loading into (boxn) ir wagons for onward transporatation to nspcl rourkela(hspg siding) | K5: Coal transport (RCR / siding) | L5: Ntpc-Sail Power Company Private Limited | M5: Orissa | N5: Rourkela | O5: 46196 | P5: Financial | Q5: - | R5: Anoop Road Carriers, Bharat Road Carrier, Godavari Commodities, Indermani / Indramani | S5: 5 named / 11 | U5: =IF(ISNUMBER(G5),MAX(MAX(G5,Settings!$B$13)*Settings!$B$7*Settings!$B$5,IF(ISNUMBER(Settings!$B$12),Settings!$B$12,0))*(1+IF(Settings!$B$11="Y",0,Settings!$B$10/100))+N(Settings!$B$9),"") | V5: 156 | W5: =IF(ISNUMBER(V5),IF(V5*Settings!$B$8>1000,"beyond table",IFERROR(LOOKUP(V5*Settings!$B$8,'FOIS 145A'!$A$2:$A$22,'FOIS 145A'!$C$2:$C$22)*(1+IF(Settings!$B$11="Y",0,Settings!$B$10/100)),"")),"") | X5: =IF(AND(ISNUMBER(U5),ISNUMBER(W5)),U5+W5,"") | Y5: =Settings!$B$6
A6: Yes | B6: mine = coal company's tender city; siding = same area | C6: Sundargarh district (IB Valley / Hemgir) (tender city) | D6: 32 | E6: Sundargarh district (IB Valley / Hemgir) (tender city) | F6: 32 | G6: 32 | H6: 17284903 | I6: GEM/2026/B/7448459 | J6: hiring of payloaders and tippers for loading and transportation of coal from stock to siding | K6: Coal transport (RCR / siding) | L6: Mahanadi Coalfields Limited | M6: Orissa | N6: Sundergarh | O6: 46144 | P6: AOC | Q6: Jagshobha Logistics Llp | S6: 5 named / 7 | T6: 2.07 | U6: =IF(ISNUMBER(G6),MAX(MAX(G6,Settings!$B$13)*Settings!$B$7*Settings!$B$5,IF(ISNUMBER(Settings!$B$12),Settings!$B$12,0))*(1+IF(Settings!$B$11="Y",0,Settings!$B$10/100))+N(Settings!$B$9),"") | W6: =IF(ISNUMBER(V6),IF(V6*Settings!$B$8>1000,"beyond table",IFERROR(LOOKUP(V6*Settings!$B$8,'FOIS 145A'!$A$2:$A$22,'FOIS 145A'!$C$2:$C$22)*(1+IF(Settings!$B$11="Y",0,Settings!$B$10/100)),"")),"") | X6: =IF(AND(ISNUMBER(U6),ISNUMBER(W6)),U6+W6,"") | Y6: =Settings!$B$6
A7: Yes | B7: mine = coal company's tender city; siding = same area | C7: Sundargarh district (IB Valley / Hemgir) (tender city) | D7: 32 | E7: Sundargarh district (IB Valley / Hemgir) (tender city) | F7: 32 | G7: 32 | H7: 16121661 | I7: GEM/2025/B/6910835 | J7: hiring of pay loaders and tippers for loading and transportation of coal from face to siding | K7: Coal transport (RCR / siding) | L7: Mahanadi Coalfields Limited | M7: Orissa | N7: Sundergarh | O7: 46003 | P7: AOC | Q7: Matarani Resources Private Limited | S7: 3 named / 3 | T7: 6.17 | U7: =IF(ISNUMBER(G7),MAX(MAX(G7,Settings!$B$13)*Settings!$B$7*Settings!$B$5,IF(ISNUMBER(Settings!$B$12),Settings!$B$12,0))*(1+IF(Settings!$B$11="Y",0,Settings!$B$10/100))+N(Settings!$B$9),"") | W7: =IF(ISNUMBER(V7),IF(V7*Settings!$B$8>1000,"beyond table",IFERROR(LOOKUP(V7*Settings!$B$8,'FOIS 145A'!$A$2:$A$22,'FOIS 145A'!$C$2:$C$22)*(1+IF(Settings!$B$11="Y",0,Settings!$B$10/100)),"")),"") | X7: =IF(AND(ISNUMBER(U7),ISNUMBER(W7)),U7+W7,"") | Y7: =Settings!$B$6
A8: Yes | B8: mine named in title; plant/siding named in title | C8: Hemgir / Manoharpur (Sundargarh) | D8: 32 | E8: Hemgir / Manoharpur (Sundargarh) | F8: 32 | G8: 32 | H8: 17034496 | I8: 2026_OCAPL_127805_1 | J8: transportation of coal from manoharpur coal mines to ntpc, darlipali, sundargarh by road | K8: Coal transport (road) | L8: Odisha Coal And Power Limited | M8: Orissa | N8: Sundergarh | O8: 46121 | P8: Technical | Q8: - | R8: Vedvyas Logistic | S8: 5 named / 5 | U8: =IF(ISNUMBER(G8),MAX(MAX(G8,Settings!$B$13)*Settings!$B$7*Settings!$B$5,IF(ISNUMBER(Settings!$B$12),Settings!$B$12,0))*(1+IF(Settings!$B$11="Y",0,Settings!$B$10/100))+N(Settings!$B$9),"") | W8: =IF(ISNUMBER(V8),IF(V8*Settings!$B$8>1000,"beyond table",IFERROR(LOOKUP(V8*Settings!$B$8,'FOIS 145A'!$A$2:$A$22,'FOIS 145A'!$C$2:$C$22)*(1+IF(Settings!$B$11="Y",0,Settings!$B$10/100)),"")),"") | X8: =IF(AND(ISNUMBER(U8),ISNUMBER(W8)),U8+W8,"") | Y8: =Settings!$B$6
A9: Yes | B9: mine named in title; plant = tender city | C9: Hemgir / Manoharpur (Sundargarh) | D9: 32 | E9: Rourkela (tender city) | F9: 156 | G9: 32 | H9: 14138047 | I9: GEM/2025/B/6302813 | J9: transportation of coal from ocpl manoharpur mines | K9: Coal transport (road) | L9: Ntpc-Sail Power Company Private Limited | M9: Orissa | N9: Rourkela | O9: 45824 | P9: AOC | Q9: Orissa Transport Co | R9: Anoop Road Carriers, Tirupati Minerals | S9: 4 named / 4 | T9: 0.39 | U9: =IF(ISNUMBER(G9),MAX(MAX(G9,Settings!$B$13)*Settings!$B$7*Settings!$B$5,IF(ISNUMBER(Settings!$B$12),Settings!$B$12,0))*(1+IF(Settings!$B$11="Y",0,Settings!$B$10/100))+N(Settings!$B$9),"") | V9: 156 | W9: =IF(ISNUMBER(V9),IF(V9*Settings!$B$8>1000,"beyond table",IFERROR(LOOKUP(V9*Settings!$B$8,'FOIS 145A'!$A$2:$A$22,'FOIS 145A'!$C$2:$C$22)*(1+IF(Settings!$B$11="Y",0,Settings!$B$10/100)),"")),"") | X9: =IF(AND(ISNUMBER(U9),ISNUMBER(W9)),U9+W9,"") | Y9: =Settings!$B$6
A10: Yes | B10: mine named in title; plant = tender city | C10: Hemgir / Manoharpur (Sundargarh) | D10: 32 | E10: Rourkela (tender city) | F10: 156 | G10: 32 | H10: 13961330 | I10: GEM/2025/B/6196170 | J10: transportation of coal from ocpl manoharpur mines to any private/public s | K10: Coal transport (road) | L10: Ntpc-Sail Power Company Private Limited | M10: Orissa | N10: Rourkela | O10: 45810 | P10: Financial | Q10: - | R10: Advika Logistics, Anoop Road Carriers, Godavari Commodities | S10: 5 named / 20 | U10: =IF(ISNUMBER(G10),MAX(MAX(G10,Settings!$B$13)*Settings!$B$7*Settings!$B$5,IF(ISNUMBER(Settings!$B$12),Settings!$B$12,0))*(1+IF(Settings!$B$11="Y",0,Settings!$B$10/100))+N(Settings!$B$9),"") | V10: 156 | W10: =IF(ISNUMBER(V10),IF(V10*Settings!$B$8>1000,"beyond table",IFERROR(LOOKUP(V10*Settings!$B$8,'FOIS 145A'!$A$2:$A$22,'FOIS 145A'!$C$2:$C$22)*(1+IF(Settings!$B$11="Y",0,Settings!$B$10/100)),"")),"") | X10: =IF(AND(ISNUMBER(U10),ISNUMBER(W10)),U10+W10,"") | Y10: =Settings!$B$6
A11: Yes | B11: mine named in title; plant = tender city | C11: Hemgir / Manoharpur (Sundargarh) | D11: 32 | E11: Rourkela (tender city) | F11: 156 | G11: 32 | H11: 13168942 | I11: GEM/2025/B/6073786 | J11: transportation of coal from ocpl manoharpur mines to any privatepublic si | K11: Coal transport (road) | L11: Ntpc-Sail Power Company Private Limited | M11: Orissa | N11: Rourkela | O11: 45750 | P11: AOC | Q11: Alps Mining Services Private Limited | R11: Anoop Road Carriers, Tirupati Minerals | S11: 3 named / 3 | T11: 0.4 | U11: =IF(ISNUMBER(G11),MAX(MAX(G11,Settings!$B$13)*Settings!$B$7*Settings!$B$5,IF(ISNUMBER(Settings!$B$12),Settings!$B$12,0))*(1+IF(Settings!$B$11="Y",0,Settings!$B$10/100))+N(Settings!$B$9),"") | V11: 156 | W11: =IF(ISNUMBER(V11),IF(V11*Settings!$B$8>1000,"beyond table",IFERROR(LOOKUP(V11*Settings!$B$8,'FOIS 145A'!$A$2:$A$22,'FOIS 145A'!$C$2:$C$22)*(1+IF(Settings!$B$11="Y",0,Settings!$B$10/100)),"")),"") | X11: =IF(AND(ISNUMBER(U11),ISNUMBER(W11)),U11+W11,"") | Y11: =Settings!$B$6
A12: Yes | B12: mine = coal company's tender city; siding = same area | C12: Sundargarh district (IB Valley / Hemgir) (tender city) | D12: 32 | E12: Sundargarh district (IB Valley / Hemgir) (tender city) | F12: 32 | G12: 32 | H12: 12921764 | I12: GEM/2025/B/5954457 | J12: loading of road sale tippe | K12: Loading / handling / crushing | L12: Mahanadi Coalfields Limited | M12: Orissa | N12: Sundergarh | O12: 45719 | P12: AOC | Q12: Millennium Suppliers Private Limited | S12: 5 named / 12 | T12: 26.98 | U12: =IF(ISNUMBER(G12),MAX(MAX(G12,Settings!$B$13)*Settings!$B$7*Settings!$B$5,IF(ISNUMBER(Settings!$B$12),Settings!$B$12,0))*(1+IF(Settings!$B$11="Y",0,Settings!$B$10/100))+N(Settings!$B$9),"") | W12: =IF(ISNUMBER(V12),IF(V12*Settings!$B$8>1000,"beyond table",IFERROR(LOOKUP(V12*Settings!$B$8,'FOIS 145A'!$A$2:$A$22,'FOIS 145A'!$C$2:$C$22)*(1+IF(Settings!$B$11="Y",0,Settings!$B$10/100)),"")),"") | X12: =IF(AND(ISNUMBER(U12),ISNUMBER(W12)),U12+W12,"") | Y12: =Settings!$B$6
A13: Yes | B13: mine = coal company's tender city; siding = same area | C13: Sundargarh district (IB Valley / Hemgir) (tender city) | D13: 32 | E13: Sundargarh district (IB Valley / Hemgir) (tender city) | F13: 32 | G13: 32 | H13: 15025805 | I13: GEM/2025/B/6419957 | J13: hiring of pay loaders and | K13: Other | L13: Mahanadi Coalfields Limited | M13: Orissa | N13: Sundergarh | O13: 45859 | P13: AOC | Q13: Matarani Resources Private Limited | R13: Saikrupa Coal Supplier | S13: 3 named / 3 | T13: 7.1 | U13: =IF(ISNUMBER(G13),MAX(MAX(G13,Settings!$B$13)*Settings!$B$7*Settings!$B$5,IF(ISNUMBER(Settings!$B$12),Settings!$B$12,0))*(1+IF(Settings!$B$11="Y",0,Settings!$B$10/100))+N(Settings!$B$9),"") | W13: =IF(ISNUMBER(V13),IF(V13*Settings!$B$8>1000,"beyond table",IFERROR(LOOKUP(V13*Settings!$B$8,'FOIS 145A'!$A$2:$A$22,'FOIS 145A'!$C$2:$C$22)*(1+IF(Settings!$B$11="Y",0,Settings!$B$10/100)),"")),"") | X13: =IF(AND(ISNUMBER(U13),ISNUMBER(W13)),U13+W13,"") | Y13: =Settings!$B$6
A14: Yes | B14: mine = coal company's tender city; siding = same area | C14: Sundargarh district (IB Valley / Hemgir) (tender city) | D14: 32 | E14: Sundargarh district (IB Valley / Hemgir) (tender city) | F14: 32 | G14: 32 | H14: 14395678 | I14: GEM/2025/B/6315435 | J14: extraction of coal/coal me | K14: Other | L14: Mahanadi Coalfields Limited | M14: Orissa | N14: Sundergarh | O14: 45848 | P14: AOC | Q14: Shree Ranisati Mining | S14: 5 named / 9 | T14: 174.14 | U14: =IF(ISNUMBER(G14),MAX(MAX(G14,Settings!$B$13)*Settings!$B$7*Settings!$B$5,IF(ISNUMBER(Settings!$B$12),Settings!$B$12,0))*(1+IF(Settings!$B$11="Y",0,Settings!$B$10/100))+N(Settings!$B$9),"") | W14: =IF(ISNUMBER(V14),IF(V14*Settings!$B$8>1000,"beyond table",IFERROR(LOOKUP(V14*Settings!$B$8,'FOIS 145A'!$A$2:$A$22,'FOIS 145A'!$C$2:$C$22)*(1+IF(Settings!$B$11="Y",0,Settings!$B$10/100)),"")),"") | X14: =IF(AND(ISNUMBER(U14),ISNUMBER(W14)),U14+W14,"") | Y14: =Settings!$B$6
A15: Yes | B15: mine = coal company's tender city; siding = same area | C15: Sundargarh district (IB Valley / Hemgir) (tender city) | D15: 32 | E15: Sundargarh district (IB Valley / Hemgir) (tender city) | F15: 32 | G15: 32 | H15: 13393053 | I15: GEM/2025/B/6129453 | J15: hiring of pay loaders & ti | K15: Other | L15: Mahanadi Coalfields Limited | M15: Orissa | N15: Sundergarh | O15: 45772 | P15: AOC | Q15: Vansh Logistics | S15: 5 named / 9 | T15: 41.46 | U15: =IF(ISNUMBER(G15),MAX(MAX(G15,Settings!$B$13)*Settings!$B$7*Settings!$B$5,IF(ISNUMBER(Settings!$B$12),Settings!$B$12,0))*(1+IF(Settings!$B$11="Y",0,Settings!$B$10/100))+N(Settings!$B$9),"") | W15: =IF(ISNUMBER(V15),IF(V15*Settings!$B$8>1000,"beyond table",IFERROR(LOOKUP(V15*Settings!$B$8,'FOIS 145A'!$A$2:$A$22,'FOIS 145A'!$C$2:$C$22)*(1+IF(Settings!$B$11="Y",0,Settings!$B$10/100)),"")),"") | X15: =IF(AND(ISNUMBER(U15),ISNUMBER(W15)),U15+W15,"") | Y15: =Settings!$B$6
A16: Yes | B16: plant = tender city | E16: Sundargarh district (IB Valley / Hemgir) (tender city) | F16: 32 | G16: 32 | H16: 12797284 | I16: GEM/2025/B/5848728 | J16: providing assistance for om activities at ntpc dlcmp | K16: Other | L16: National Thermal Power Corporation Limited | M16: Orissa | N16: Sundergarh | O16: 45713 | P16: AOC | Q16: M/S A P Construction | S16: 5 named / 9 | T16: 2.19 | U16: =IF(ISNUMBER(G16),MAX(MAX(G16,Settings!$B$13)*Settings!$B$7*Settings!$B$5,IF(ISNUMBER(Settings!$B$12),Settings!$B$12,0))*(1+IF(Settings!$B$11="Y",0,Settings!$B$10/100))+N(Settings!$B$9),"") | W16: =IF(ISNUMBER(V16),IF(V16*Settings!$B$8>1000,"beyond table",IFERROR(LOOKUP(V16*Settings!$B$8,'FOIS 145A'!$A$2:$A$22,'FOIS 145A'!$C$2:$C$22)*(1+IF(Settings!$B$11="Y",0,Settings!$B$10/100)),"")),"") | X16: =IF(AND(ISNUMBER(U16),ISNUMBER(W16)),U16+W16,"") | Y16: =Settings!$B$6
A17: Yes | B17: mine named in title | C17: IB Valley (Jharsuguda) | D17: 47 | G17: 47 | H17: 18286647 | I17: 2026_NTPC_111971_1 | J17: contract for loading and transportation of coal from mcl-ib mine to any designated siding and loading in indian railway wagons for onward transportation to ntpc simhadri. | K17: Coal transport (RCR / siding) | L17: National Thermal Power Corporation Limited | M17: Andhra Pradesh | N17: Visakhapatnam | O17: 46274 | P17: Financial | Q17: - | R17: Anoop Road Carriers, Bharat Road Carrier, Sangita Sales, Swami Fuels | S17: 5 named / 6 | U17: =IF(ISNUMBER(G17),MAX(MAX(G17,Settings!$B$13)*Settings!$B$7*Settings!$B$5,IF(ISNUMBER(Settings!$B$12),Settings!$B$12,0))*(1+IF(Settings!$B$11="Y",0,Settings!$B$10/100))+N(Settings!$B$9),"") | W17: =IF(ISNUMBER(V17),IF(V17*Settings!$B$8>1000,"beyond table",IFERROR(LOOKUP(V17*Settings!$B$8,'FOIS 145A'!$A$2:$A$22,'FOIS 145A'!$C$2:$C$22)*(1+IF(Settings!$B$11="Y",0,Settings!$B$10/100)),"")),"") | X17: =IF(AND(ISNUMBER(U17),ISNUMBER(W17)),U17+W17,"") | Y17: =Settings!$B$6
A18: Yes | B18: mine = coal company's tender city; siding = same area | C18: Brajrajnagar / Jharsuguda (tender city) | D18: 54 | E18: Brajrajnagar / Jharsuguda (tender city) | F18: 54 | G18: 54 | H18: 12706783 | I18: GEM/2025/B/5868534 | J18: loading and transportation | K18: Coal transport (road) | L18: Mahanadi Coalfields Limited | M18: Orissa | N18: Jharsuguda | O18: 45708 | P18: AOC | Q18: Variant Commercial Private Limited | S18: 5 named / 11 | T18: 94.21 | U18: =IF(ISNUMBER(G18),MAX(MAX(G18,Settings!$B$13)*Settings!$B$7*Settings!$B$5,IF(ISNUMBER(Settings!$B$12),Settings!$B$12,0))*(1+IF(Settings!$B$11="Y",0,Settings!$B$10/100))+N(Settings!$B$9),"") | W18: =IF(ISNUMBER(V18),IF(V18*Settings!$B$8>1000,"beyond table",IFERROR(LOOKUP(V18*Settings!$B$8,'FOIS 145A'!$A$2:$A$22,'FOIS 145A'!$C$2:$C$22)*(1+IF(Settings!$B$11="Y",0,Settings!$B$10/100)),"")),"") | X18: =IF(AND(ISNUMBER(U18),ISNUMBER(W18)),U18+W18,"") | Y18: =Settings!$B$6
A19: Yes | B19: mine named in title | C19: Talabira (near Sambalpur/Jharsuguda) | D19: 61 | G19: 61 | H19: 18306349 | I19: 2026_NTPC_111933_1 | J19: transportation of 2 lmt coal from nlc talabira mines to ntpc simhadri through rcr mode - as per sow | K19: Coal transport (RCR / siding) | L19: National Thermal Power Corporation Limited | M19: Chhattisgarh | N19: Raipur | O19: 46288 | P19: Financial | Q19: - | R19: Anoop Road Carriers, Bharat Road Carrier, Mohit Minerals, Sangita Sales | S19: 5 named / 8 | U19: =IF(ISNUMBER(G19),MAX(MAX(G19,Settings!$B$13)*Settings!$B$7*Settings!$B$5,IF(ISNUMBER(Settings!$B$12),Settings!$B$12,0))*(1+IF(Settings!$B$11="Y",0,Settings!$B$10/100))+N(Settings!$B$9),"") | W19: =IF(ISNUMBER(V19),IF(V19*Settings!$B$8>1000,"beyond table",IFERROR(LOOKUP(V19*Settings!$B$8,'FOIS 145A'!$A$2:$A$22,'FOIS 145A'!$C$2:$C$22)*(1+IF(Settings!$B$11="Y",0,Settings!$B$10/100)),"")),"") | X19: =IF(AND(ISNUMBER(U19),ISNUMBER(W19)),U19+W19,"") | Y19: =Settings!$B$6
A20: Yes | B20: mine named in title; plant/siding named in title | C20: Talabira (near Sambalpur/Jharsuguda) | D20: 61 | E20: Talabira (near Sambalpur/Jharsuguda) | F20: 61 | G20: 61 | H20: 18286732 | I20: 2026_NTPC_111957_1 | J20: coal transportation from nlc talabira mines to ntpc telangana(ttgr) - coal transportation from nlc talabira mines to ntpc telangana(ttgr)through rcr mode | K20: Coal transport (RCR / siding) | L20: National Thermal Power Corporation Limited | M20: Chhattisgarh | N20: Raipur | O20: 46287 | P20: AOC | Q20: Swami Fuels Private Limited | R20: Anoop Road Carriers, Swami Fuels, Tirupati Minerals | S20: 4 named / 4 | T20: 6.68 | U20: =IF(ISNUMBER(G20),MAX(MAX(G20,Settings!$B$13)*Settings!$B$7*Settings!$B$5,IF(ISNUMBER(Settings!$B$12),Settings!$B$12,0))*(1+IF(Settings!$B$11="Y",0,Settings!$B$10/100))+N(Settings!$B$9),"") | W20: =IF(ISNUMBER(V20),IF(V20*Settings!$B$8>1000,"beyond table",IFERROR(LOOKUP(V20*Settings!$B$8,'FOIS 145A'!$A$2:$A$22,'FOIS 145A'!$C$2:$C$22)*(1+IF(Settings!$B$11="Y",0,Settings!$B$10/100)),"")),"") | X20: =IF(AND(ISNUMBER(U20),ISNUMBER(W20)),U20+W20,"") | Y20: =Settings!$B$6
A21: Yes | B21: mine named in title | C21: Talabira (near Sambalpur/Jharsuguda) | D21: 61 | G21: 61 | H21: 18222478 | I21: 2026_NTPC_111805_1 | J21: coal transportation from nlc talabira mines to ntpc kudgi through rcr | K21: Coal transport (RCR / siding) | L21: National Thermal Power Corporation Limited | M21: Karnataka | N21: Kudligi | O21: 46156 | P21: AOC | Q21: Kalyani Ventures Limited | S21: 1 named / 1 | T21: 1.5 | U21: =IF(ISNUMBER(G21),MAX(MAX(G21,Settings!$B$13)*Settings!$B$7*Settings!$B$5,IF(ISNUMBER(Settings!$B$12),Settings!$B$12,0))*(1+IF(Settings!$B$11="Y",0,Settings!$B$10/100))+N(Settings!$B$9),"") | W21: =IF(ISNUMBER(V21),IF(V21*Settings!$B$8>1000,"beyond table",IFERROR(LOOKUP(V21*Settings!$B$8,'FOIS 145A'!$A$2:$A$22,'FOIS 145A'!$C$2:$C$22)*(1+IF(Settings!$B$11="Y",0,Settings!$B$10/100)),"")),"") | X21: =IF(AND(ISNUMBER(U21),ISNUMBER(W21)),U21+W21,"") | Y21: =Settings!$B$6
A22: Yes | B22: mine named in title; plant = tender city in West Bengal | C22: Talabira (near Sambalpur/Jharsuguda) | D22: 61 | G22: 61 | H22: 15407506 | I22: 2025_DVC_245419_1 | J22: lifting of 20.0(twenty) lmt coal from nlc india limited (nlcil)-talabira ii and iii ocp, sambalpur, odisha to dstps and other tps of dvc through rcr mode | K22: Coal transport (RCR / siding) | L22: Damodar Valley Corporation | M22: West Bengal | N22: Kolkata | O22: 45897 | P22: Technical | Q22: - | R22: Anoop Road Carriers, Godavari Commodities | S22: 5 named / 17 | U22: =IF(ISNUMBER(G22),MAX(MAX(G22,Settings!$B$13)*Settings!$B$7*Settings!$B$5,IF(ISNUMBER(Settings!$B$12),Settings!$B$12,0))*(1+IF(Settings!$B$11="Y",0,Settings!$B$10/100))+N(Settings!$B$9),"") | W22: =IF(ISNUMBER(V22),IF(V22*Settings!$B$8>1000,"beyond table",IFERROR(LOOKUP(V22*Settings!$B$8,'FOIS 145A'!$A$2:$A$22,'FOIS 145A'!$C$2:$C$22)*(1+IF(Settings!$B$11="Y",0,Settings!$B$10/100)),"")),"") | X22: =IF(AND(ISNUMBER(U22),ISNUMBER(W22)),U22+W22,"") | Y22: =Settings!$B$6
A23: Yes | B23: mine named in title | C23: Talabira (near Sambalpur/Jharsuguda) | D23: 61 | G23: 61 | H23: 14761261 | I23: 2025_NTPC_98583_1 | J23: transportation of 300000mt coal from nlc talabira mines of nlc ltd to ntpc simhadri under rcr mode through any nearby siding | K23: Coal transport (RCR / siding) | L23: National Thermal Power Corporation Limited | M23: Andhra Pradesh | N23: Visakhapatnam | O23: 45880 | P23: Technical | Q23: - | R23: Advika Logistics, Anoop Road Carriers, Indermani / Indramani | S23: 5 named / 15 | U23: =IF(ISNUMBER(G23),MAX(MAX(G23,Settings!$B$13)*Settings!$B$7*Settings!$B$5,IF(ISNUMBER(Settings!$B$12),Settings!$B$12,0))*(1+IF(Settings!$B$11="Y",0,Settings!$B$10/100))+N(Settings!$B$9),"") | W23: =IF(ISNUMBER(V23),IF(V23*Settings!$B$8>1000,"beyond table",IFERROR(LOOKUP(V23*Settings!$B$8,'FOIS 145A'!$A$2:$A$22,'FOIS 145A'!$C$2:$C$22)*(1+IF(Settings!$B$11="Y",0,Settings!$B$10/100)),"")),"") | X23: =IF(AND(ISNUMBER(U23),ISNUMBER(W23)),U23+W23,"") | Y23: =Settings!$B$6
A24: Yes | B24: mine named in title; plant/siding named in title | C24: Dharamjaigarh (Raigarh) | D24: 66 | E24: Dharamjaigarh (Raigarh) | F24: 66 | G24: 66 | H24: 15913239 | I24: GEM/2025/B/6876204 | J24: loading, transportation & unloading and wagon loading of coal from surface coal yard of tlcmp to kchp | K24: Coal transport (RCR / siding) | L24: National Thermal Power Corporation Limited | M24: Chhattisgarh | N24: Raigarh | O24: 45999 | P24: AOC | Q24: A B Carriers | R24: Anoop Road Carriers, Mohit Minerals, Nkas Services, Orissa Stevedores | S24: 5 named / 10 | T24: 9.08 | U24: =IF(ISNUMBER(G24),MAX(MAX(G24,Settings!$B$13)*Settings!$B$7*Settings!$B$5,IF(ISNUMBER(Settings!$B$12),Settings!$B$12,0))*(1+IF(Settings!$B$11="Y",0,Settings!$B$10/100))+N(Settings!$B$9),"") | W24: =IF(ISNUMBER(V24),IF(V24*Settings!$B$8>1000,"beyond table",IFERROR(LOOKUP(V24*Settings!$B$8,'FOIS 145A'!$A$2:$A$22,'FOIS 145A'!$C$2:$C$22)*(1+IF(Settings!$B$11="Y",0,Settings!$B$10/100)),"")),"") | X24: =IF(AND(ISNUMBER(U24),ISNUMBER(W24)),U24+W24,"") | Y24: =Settings!$B$6
A25: Yes | B25: mine named in title; plant = tender city in Maharashtra | C25: Dharamjaigarh (Raigarh) | D25: 66 | G25: 66 | H25: 14761268 | I25: 2025_NTPC_98502_1 | J25: coal transportation (20 lmt) from talaipalli mines to mouda stps under rcr mode via korichhapar siding | K25: Coal transport (RCR / siding) | L25: National Thermal Power Corporation Limited | M25: Maharashtra | N25: Nagpur | O25: 45870 | P25: Financial | Q25: - | R25: Anoop Road Carriers, Godavari Commodities, Indermani / Indramani | S25: 5 named / 20 | U25: =IF(ISNUMBER(G25),MAX(MAX(G25,Settings!$B$13)*Settings!$B$7*Settings!$B$5,IF(ISNUMBER(Settings!$B$12),Settings!$B$12,0))*(1+IF(Settings!$B$11="Y",0,Settings!$B$10/100))+N(Settings!$B$9),"") | W25: =IF(ISNUMBER(V25),IF(V25*Settings!$B$8>1000,"beyond table",IFERROR(LOOKUP(V25*Settings!$B$8,'FOIS 145A'!$A$2:$A$22,'FOIS 145A'!$C$2:$C$22)*(1+IF(Settings!$B$11="Y",0,Settings!$B$10/100)),"")),"") | X25: =IF(AND(ISNUMBER(U25),ISNUMBER(W25)),U25+W25,"") | Y25: =Settings!$B$6
A26: Yes | B26: plant/siding named in title | E26: Dharamjaigarh (Raigarh) | F26: 66 | G26: 66 | H26: 16814789 | I26: GEM/2026/B/7315717 | J26: coal transportation from ramnagore colliery to nspcl durgapur | K26: Coal transport (road) | L26: Ntpc-Sail Power Company Private Limited | M26: West Bengal | N26: Durgapur | O26: 46097 | P26: AOC | Q26: M/S United Coal Carriers | R26: United Coal Carriers | S26: 5 named / 5 | T26: 0.21 | U26: =IF(ISNUMBER(G26),MAX(MAX(G26,Settings!$B$13)*Settings!$B$7*Settings!$B$5,IF(ISNUMBER(Settings!$B$12),Settings!$B$12,0))*(1+IF(Settings!$B$11="Y",0,Settings!$B$10/100))+N(Settings!$B$9),"") | W26: =IF(ISNUMBER(V26),IF(V26*Settings!$B$8>1000,"beyond table",IFERROR(LOOKUP(V26*Settings!$B$8,'FOIS 145A'!$A$2:$A$22,'FOIS 145A'!$C$2:$C$22)*(1+IF(Settings!$B$11="Y",0,Settings!$B$10/100)),"")),"") | X26: =IF(AND(ISNUMBER(U26),ISNUMBER(W26)),U26+W26,"") | Y26: =Settings!$B$6
A27: Yes | B27: mine named in title | C27: Dharamjaigarh (Raigarh) | D27: 66 | G27: 66 | H27: 17065555 | I27: GEM/2026/B/7067958 | J27: handling service, handling & transport service, ob removal, coal extraction, composite work for ob removal cutting loading transportation wagon loading of coal at durgapur ocm r.. | K27: Mining services (OB / extraction) | L27: South Eastern Coalfields Limited | M27: Chhattisgarh | N27: Raigarh | O27: 46081 | P27: AOC | Q27: Sunil Kumar Agrawal | S27: 5 named / 11 | T27: 4247.08 | U27: =IF(ISNUMBER(G27),MAX(MAX(G27,Settings!$B$13)*Settings!$B$7*Settings!$B$5,IF(ISNUMBER(Settings!$B$12),Settings!$B$12,0))*(1+IF(Settings!$B$11="Y",0,Settings!$B$10/100))+N(Settings!$B$9),"") | W27: =IF(ISNUMBER(V27),IF(V27*Settings!$B$8>1000,"beyond table",IFERROR(LOOKUP(V27*Settings!$B$8,'FOIS 145A'!$A$2:$A$22,'FOIS 145A'!$C$2:$C$22)*(1+IF(Settings!$B$11="Y",0,Settings!$B$10/100)),"")),"") | X27: =IF(AND(ISNUMBER(U27),ISNUMBER(W27)),U27+W27,"") | Y27: =Settings!$B$6
A28: Yes | B28: mine = coal company's tender city; siding = same area | C28: Sambalpur (tender city) | D28: 77 | E28: Sambalpur (tender city) | F28: 77 | G28: 77 | H28: 12395907 | I28: GEM/2024/B/5759091 | J28: coal loading and transport | K28: Coal transport (road) | L28: Mahanadi Coalfields Limited | M28: Orissa | N28: Sambalpur | O28: 45670 | P28: AOC | Q28: Vlt Associates | S28: 5 named / 10 | T28: 28 | U28: =IF(ISNUMBER(G28),MAX(MAX(G28,Settings!$B$13)*Settings!$B$7*Settings!$B$5,IF(ISNUMBER(Settings!$B$12),Settings!$B$12,0))*(1+IF(Settings!$B$11="Y",0,Settings!$B$10/100))+N(Settings!$B$9),"") | W28: =IF(ISNUMBER(V28),IF(V28*Settings!$B$8>1000,"beyond table",IFERROR(LOOKUP(V28*Settings!$B$8,'FOIS 145A'!$A$2:$A$22,'FOIS 145A'!$C$2:$C$22)*(1+IF(Settings!$B$11="Y",0,Settings!$B$10/100)),"")),"") | X28: =IF(AND(ISNUMBER(U28),ISNUMBER(W28)),U28+W28,"") | Y28: =Settings!$B$6
A29: Yes | B29: mine = coal company's tender city; siding = same area | C29: Korba (tender city) | D29: 88 | E29: Korba (tender city) | F29: 88 | G29: 88 | H29: 16687336 | I29: GEM/2025/B/7005420 | J29: handling & transport service, transport service, handling service, hiring of pay loader and tippers for coal loading at saraipali transportation and loading into wagons at korba.. | K29: Coal transport (RCR / siding) | L29: South Eastern Coalfields Limited | M29: Chhattisgarh | N29: Korba | O29: 46024 | P29: AOC | Q29: G K Associates | R29: G K Associates | S29: 5 named / 30 | T29: 329.87 | U29: =IF(ISNUMBER(G29),MAX(MAX(G29,Settings!$B$13)*Settings!$B$7*Settings!$B$5,IF(ISNUMBER(Settings!$B$12),Settings!$B$12,0))*(1+IF(Settings!$B$11="Y",0,Settings!$B$10/100))+N(Settings!$B$9),"") | W29: =IF(ISNUMBER(V29),IF(V29*Settings!$B$8>1000,"beyond table",IFERROR(LOOKUP(V29*Settings!$B$8,'FOIS 145A'!$A$2:$A$22,'FOIS 145A'!$C$2:$C$22)*(1+IF(Settings!$B$11="Y",0,Settings!$B$10/100)),"")),"") | X29: =IF(AND(ISNUMBER(U29),ISNUMBER(W29)),U29+W29,"") | Y29: =Settings!$B$6
A30: Yes | B30: mine named in title; plant/siding named in title | C30: Korba | D30: 88 | E30: Korba | F30: 88 | G30: 88 | H30: 16125779 | I30: GEM/2025/B/6972824 | J30: handling & transport service, coal loading & transportation from saraipali ocm to srk rl siding, korba | K30: Coal transport (RCR / siding) | L30: South Eastern Coalfields Limited | M30: Chhattisgarh | N30: Korba | O30: 46013 | P30: AOC | Q30: M/S Chandan Kumar Singh | R30: G K Associates, Chandan Kumar Singh | S30: 5 named / 7 | T30: 1.58 | U30: =IF(ISNUMBER(G30),MAX(MAX(G30,Settings!$B$13)*Settings!$B$7*Settings!$B$5,IF(ISNUMBER(Settings!$B$12),Settings!$B$12,0))*(1+IF(Settings!$B$11="Y",0,Settings!$B$10/100))+N(Settings!$B$9),"") | W30: =IF(ISNUMBER(V30),IF(V30*Settings!$B$8>1000,"beyond table",IFERROR(LOOKUP(V30*Settings!$B$8,'FOIS 145A'!$A$2:$A$22,'FOIS 145A'!$C$2:$C$22)*(1+IF(Settings!$B$11="Y",0,Settings!$B$10/100)),"")),"") | X30: =IF(AND(ISNUMBER(U30),ISNUMBER(W30)),U30+W30,"") | Y30: =Settings!$B$6
A31: Yes | B31: mine named in title | C31: Korba | D31: 88 | G31: 88 | H31: 16687380 | I31: GEM/2026/B/7114126 | J31: hiring of pay loaders and tippers for mechanical loading and transportation of coal at dipka oc expansion project, dipka area, secl for a period of 1096 days | K31: Coal transport (road) | L31: South Eastern Coalfields Limited | M31: Chhattisgarh | N31: Korba | O31: 46053 | P31: AOC | Q31: Maa Parwati Transport | S31: 5 named / 9 | T31: 90.24 | U31: =IF(ISNUMBER(G31),MAX(MAX(G31,Settings!$B$13)*Settings!$B$7*Settings!$B$5,IF(ISNUMBER(Settings!$B$12),Settings!$B$12,0))*(1+IF(Settings!$B$11="Y",0,Settings!$B$10/100))+N(Settings!$B$9),"") | W31: =IF(ISNUMBER(V31),IF(V31*Settings!$B$8>1000,"beyond table",IFERROR(LOOKUP(V31*Settings!$B$8,'FOIS 145A'!$A$2:$A$22,'FOIS 145A'!$C$2:$C$22)*(1+IF(Settings!$B$11="Y",0,Settings!$B$10/100)),"")),"") | X31: =IF(AND(ISNUMBER(U31),ISNUMBER(W31)),U31+W31,"") | Y31: =Settings!$B$6
A32: Yes | B32: mine named in title | C32: Korba | D32: 88 | G32: 88 | H32: 16786403 | I32: GEM/2025/B/6972482 | J32: hiring of pay loader, mobile crusher and tippers for transportation of coal at gevra area secl | K32: Coal transport (road) | L32: South Eastern Coalfields Limited | M32: Chhattisgarh | N32: Korba | O32: 46023 | P32: AOC | Q32: Vikas Coal And Minerals Private Limited | R32: G K Associates | S32: 5 named / 16 | T32: 140.8 | U32: =IF(ISNUMBER(G32),MAX(MAX(G32,Settings!$B$13)*Settings!$B$7*Settings!$B$5,IF(ISNUMBER(Settings!$B$12),Settings!$B$12,0))*(1+IF(Settings!$B$11="Y",0,Settings!$B$10/100))+N(Settings!$B$9),"") | W32: =IF(ISNUMBER(V32),IF(V32*Settings!$B$8>1000,"beyond table",IFERROR(LOOKUP(V32*Settings!$B$8,'FOIS 145A'!$A$2:$A$22,'FOIS 145A'!$C$2:$C$22)*(1+IF(Settings!$B$11="Y",0,Settings!$B$10/100)),"")),"") | X32: =IF(AND(ISNUMBER(U32),ISNUMBER(W32)),U32+W32,"") | Y32: =Settings!$B$6
A33: Yes | B33: mine = coal company's tender city; siding = same area | C33: Korba (tender city) | D33: 88 | E33: Korba (tender city) | F33: 88 | G33: 88 | H33: 15830605 | I33: GEM/2025/B/6869302 | J33: loading and transportation of coal | K33: Coal transport (road) | L33: South Eastern Coalfields Limited | M33: Chhattisgarh | N33: Korba | O33: 45989 | P33: AOC | Q33: G K Associates | R33: G K Associates | S33: 3 named / 3 | T33: 1.67 | U33: =IF(ISNUMBER(G33),MAX(MAX(G33,Settings!$B$13)*Settings!$B$7*Settings!$B$5,IF(ISNUMBER(Settings!$B$12),Settings!$B$12,0))*(1+IF(Settings!$B$11="Y",0,Settings!$B$10/100))+N(Settings!$B$9),"") | W33: =IF(ISNUMBER(V33),IF(V33*Settings!$B$8>1000,"beyond table",IFERROR(LOOKUP(V33*Settings!$B$8,'FOIS 145A'!$A$2:$A$22,'FOIS 145A'!$C$2:$C$22)*(1+IF(Settings!$B$11="Y",0,Settings!$B$10/100)),"")),"") | X33: =IF(AND(ISNUMBER(U33),ISNUMBER(W33)),U33+W33,"") | Y33: =Settings!$B$6
A34: Yes | B34: mine = coal company's tender city; siding = same area | C34: Korba (tender city) | D34: 88 | E34: Korba (tender city) | F34: 88 | G34: 88 | H34: 14287776 | I34: GEM/2025/B/6337006 | J34: loading and transportation | K34: Coal transport (road) | L34: South Eastern Coalfields Limited | M34: Chhattisgarh | N34: Korba | O34: 45836 | P34: AOC | Q34: Rakesh Kumar Enterprises | R34: G K Associates | S34: 5 named / 6 | T34: 1.9 | U34: =IF(ISNUMBER(G34),MAX(MAX(G34,Settings!$B$13)*Settings!$B$7*Settings!$B$5,IF(ISNUMBER(Settings!$B$12),Settings!$B$12,0))*(1+IF(Settings!$B$11="Y",0,Settings!$B$10/100))+N(Settings!$B$9),"") | W34: =IF(ISNUMBER(V34),IF(V34*Settings!$B$8>1000,"beyond table",IFERROR(LOOKUP(V34*Settings!$B$8,'FOIS 145A'!$A$2:$A$22,'FOIS 145A'!$C$2:$C$22)*(1+IF(Settings!$B$11="Y",0,Settings!$B$10/100)),"")),"") | X34: =IF(AND(ISNUMBER(U34),ISNUMBER(W34)),U34+W34,"") | Y34: =Settings!$B$6
A35: Yes | B35: mine named in title | C35: Korba | D35: 88 | G35: 88 | H35: 17670369 | I35: GEM/2026/B/7435893 | J35: handling service, excavator with crusher bucket system with screening and loading of coal into tippers at kusmunda oc kusmunda area | K35: Loading / handling / crushing | L35: South Eastern Coalfields Limited | M35: Chhattisgarh | N35: Korba | O35: 46156 | P35: AOC | Q35: Fsnl Private Limited, Maa Sarwamangla Transport Company | S35: 5 named / 8 | T35: 24.94 | U35: =IF(ISNUMBER(G35),MAX(MAX(G35,Settings!$B$13)*Settings!$B$7*Settings!$B$5,IF(ISNUMBER(Settings!$B$12),Settings!$B$12,0))*(1+IF(Settings!$B$11="Y",0,Settings!$B$10/100))+N(Settings!$B$9),"") | W35: =IF(ISNUMBER(V35),IF(V35*Settings!$B$8>1000,"beyond table",IFERROR(LOOKUP(V35*Settings!$B$8,'FOIS 145A'!$A$2:$A$22,'FOIS 145A'!$C$2:$C$22)*(1+IF(Settings!$B$11="Y",0,Settings!$B$10/100)),"")),"") | X35: =IF(AND(ISNUMBER(U35),ISNUMBER(W35)),U35+W35,"") | Y35: =Settings!$B$6
A36: Yes | B36: mine = coal company's tender city; siding = same area | C36: Korba (tender city) | D36: 88 | E36: Korba (tender city) | F36: 88 | G36: 88 | H36: 15659451 | I36: GEM/2025/B/6627991 | J36: handling service, transpor | K36: Loading / handling / crushing | L36: South Eastern Coalfields Limited | M36: Chhattisgarh | N36: Korba | O36: 45923 | P36: AOC | Q36: Harsh Roadlines Private Limited | R36: Orissa Stevedores | S36: 5 named / 8 | T36: 82.78 | U36: =IF(ISNUMBER(G36),MAX(MAX(G36,Settings!$B$13)*Settings!$B$7*Settings!$B$5,IF(ISNUMBER(Settings!$B$12),Settings!$B$12,0))*(1+IF(Settings!$B$11="Y",0,Settings!$B$10/100))+N(Settings!$B$9),"") | W36: =IF(ISNUMBER(V36),IF(V36*Settings!$B$8>1000,"beyond table",IFERROR(LOOKUP(V36*Settings!$B$8,'FOIS 145A'!$A$2:$A$22,'FOIS 145A'!$C$2:$C$22)*(1+IF(Settings!$B$11="Y",0,Settings!$B$10/100)),"")),"") | X36: =IF(AND(ISNUMBER(U36),ISNUMBER(W36)),U36+W36,"") | Y36: =Settings!$B$6
A37: Yes | B37: mine = coal company's tender city; siding = same area | C37: Korba (tender city) | D37: 88 | E37: Korba (tender city) | F37: 88 | G37: 88 | H37: 17304517 | I37: GEM/2026/B/7372908 | J37: handling service, transport service, handling & transport service, ob removal, composite work for ob removal coal cutting by surface miner and loading and transportation of coal.. | K37: Mining services (OB / extraction) | L37: South Eastern Coalfields Limited | M37: Chhattisgarh | N37: Korba | O37: 46135 | P37: AOC | Q37: Knr Constructions Limited | S37: 5 named / 8 | T37: 3966.12 | U37: =IF(ISNUMBER(G37),MAX(MAX(G37,Settings!$B$13)*Settings!$B$7*Settings!$B$5,IF(ISNUMBER(Settings!$B$12),Settings!$B$12,0))*(1+IF(Settings!$B$11="Y",0,Settings!$B$10/100))+N(Settings!$B$9),"") | W37: =IF(ISNUMBER(V37),IF(V37*Settings!$B$8>1000,"beyond table",IFERROR(LOOKUP(V37*Settings!$B$8,'FOIS 145A'!$A$2:$A$22,'FOIS 145A'!$C$2:$C$22)*(1+IF(Settings!$B$11="Y",0,Settings!$B$10/100)),"")),"") | X37: =IF(AND(ISNUMBER(U37),ISNUMBER(W37)),U37+W37,"") | Y37: =Settings!$B$6
A38: Yes | B38: mine named in title | C38: Korba | D38: 88 | G38: 88 | H38: 16765105 | I38: GEM/2025/B/7003673 | J38: ob removal, handling & transport service, hiring of hemm for ob removal and coal drilling with loading and transportation at manikpur ocp korba area | K38: Mining services (OB / extraction) | L38: South Eastern Coalfields Limited | M38: Chhattisgarh | N38: Korba | O38: 46043 | P38: AOC | Q38: Orissa Stevedores Limited | S38: 5 named / 10 | T38: 1775.85 | U38: =IF(ISNUMBER(G38),MAX(MAX(G38,Settings!$B$13)*Settings!$B$7*Settings!$B$5,IF(ISNUMBER(Settings!$B$12),Settings!$B$12,0))*(1+IF(Settings!$B$11="Y",0,Settings!$B$10/100))+N(Settings!$B$9),"") | W38: =IF(ISNUMBER(V38),IF(V38*Settings!$B$8>1000,"beyond table",IFERROR(LOOKUP(V38*Settings!$B$8,'FOIS 145A'!$A$2:$A$22,'FOIS 145A'!$C$2:$C$22)*(1+IF(Settings!$B$11="Y",0,Settings!$B$10/100)),"")),"") | X38: =IF(AND(ISNUMBER(U38),ISNUMBER(W38)),U38+W38,"") | Y38: =Settings!$B$6
A39: Yes | B39: mine = coal company's tender city; siding = same area | C39: Korba (tender city) | D39: 88 | E39: Korba (tender city) | F39: 88 | G39: 88 | H39: 16245601 | I39: GEM/2025/B/6729097 | J39: hiring of pay loader incorporated with weight sensors for mechanical transfer of coal into railway wagons for a quantity of 17520000 te with minimum tpd16000 te for a period of .. | K39: Other | L39: South Eastern Coalfields Limited | M39: Chhattisgarh | N39: Korba | O39: 45948 | P39: AOC | Q39: Sat Kartar Logistics | S39: 5 named / 19 | T39: 14.89 | U39: =IF(ISNUMBER(G39),MAX(MAX(G39,Settings!$B$13)*Settings!$B$7*Settings!$B$5,IF(ISNUMBER(Settings!$B$12),Settings!$B$12,0))*(1+IF(Settings!$B$11="Y",0,Settings!$B$10/100))+N(Settings!$B$9),"") | W39: =IF(ISNUMBER(V39),IF(V39*Settings!$B$8>1000,"beyond table",IFERROR(LOOKUP(V39*Settings!$B$8,'FOIS 145A'!$A$2:$A$22,'FOIS 145A'!$C$2:$C$22)*(1+IF(Settings!$B$11="Y",0,Settings!$B$10/100)),"")),"") | X39: =IF(AND(ISNUMBER(U39),ISNUMBER(W39)),U39+W39,"") | Y39: =Settings!$B$6
A40: Yes | B40: mine = coal company's tender city; siding = same area | C40: Korba (tender city) | D40: 88 | E40: Korba (tender city) | F40: 88 | G40: 88 | H40: 12743621 | I40: GEM/2025/B/5926593 | J40: hiring of payloaders and t | K40: Other | L40: South Eastern Coalfields Limited | M40: Chhattisgarh | N40: Korba | O40: 45712 | P40: AOC | Q40: Harsh Roadlines Private Limited | S40: 5 named / 7 | T40: 2.41 | U40: =IF(ISNUMBER(G40),MAX(MAX(G40,Settings!$B$13)*Settings!$B$7*Settings!$B$5,IF(ISNUMBER(Settings!$B$12),Settings!$B$12,0))*(1+IF(Settings!$B$11="Y",0,Settings!$B$10/100))+N(Settings!$B$9),"") | W40: =IF(ISNUMBER(V40),IF(V40*Settings!$B$8>1000,"beyond table",IFERROR(LOOKUP(V40*Settings!$B$8,'FOIS 145A'!$A$2:$A$22,'FOIS 145A'!$C$2:$C$22)*(1+IF(Settings!$B$11="Y",0,Settings!$B$10/100)),"")),"") | X40: =IF(AND(ISNUMBER(U40),ISNUMBER(W40)),U40+W40,"") | Y40: =Settings!$B$6
A41: Yes | B41: mine = coal company's tender city; siding = same area | C41: Bilaspur / Sipat (tender city) | D41: 130 | E41: Bilaspur / Sipat (tender city) | F41: 130 | G41: 130 | H41: 13684513 | I41: GEM/2025/B/6210677 | J41: handling & transport servi | K41: Coal transport (road) | L41: South Eastern Coalfields Limited | M41: Chhattisgarh | N41: Bilaspur | O41: 45801 | P41: AOC | Q41: Sat Kartar Logistics | R41: G K Associates | S41: 5 named / 16 | T41: 63.2 | U41: =IF(ISNUMBER(G41),MAX(MAX(G41,Settings!$B$13)*Settings!$B$7*Settings!$B$5,IF(ISNUMBER(Settings!$B$12),Settings!$B$12,0))*(1+IF(Settings!$B$11="Y",0,Settings!$B$10/100))+N(Settings!$B$9),"") | W41: =IF(ISNUMBER(V41),IF(V41*Settings!$B$8>1000,"beyond table",IFERROR(LOOKUP(V41*Settings!$B$8,'FOIS 145A'!$A$2:$A$22,'FOIS 145A'!$C$2:$C$22)*(1+IF(Settings!$B$11="Y",0,Settings!$B$10/100)),"")),"") | X41: =IF(AND(ISNUMBER(U41),ISNUMBER(W41)),U41+W41,"") | Y41: =Settings!$B$6
A42: Yes | B42: mine = coal company's tender city; siding = same area | C42: Bilaspur / Sipat (tender city) | D42: 130 | E42: Bilaspur / Sipat (tender city) | F42: 130 | G42: 130 | H42: 12395784 | I42: GEM/2024/B/5755957 | J42: loading transportation of | K42: Coal transport (road) | L42: South Eastern Coalfields Limited | M42: Chhattisgarh | N42: Bilaspur | O42: 45670 | P42: AOC | Q42: Agro Fuel Corporation | R42: G K Associates | S42: 3 named / 3 | T42: 13.4 | U42: =IF(ISNUMBER(G42),MAX(MAX(G42,Settings!$B$13)*Settings!$B$7*Settings!$B$5,IF(ISNUMBER(Settings!$B$12),Settings!$B$12,0))*(1+IF(Settings!$B$11="Y",0,Settings!$B$10/100))+N(Settings!$B$9),"") | W42: =IF(ISNUMBER(V42),IF(V42*Settings!$B$8>1000,"beyond table",IFERROR(LOOKUP(V42*Settings!$B$8,'FOIS 145A'!$A$2:$A$22,'FOIS 145A'!$C$2:$C$22)*(1+IF(Settings!$B$11="Y",0,Settings!$B$10/100)),"")),"") | X42: =IF(AND(ISNUMBER(U42),ISNUMBER(W42)),U42+W42,"") | Y42: =Settings!$B$6
A43: Yes | B43: mine named in title; plant/siding named in title | C43: Ambikapur / Surguja | D43: 137 | E43: Ambikapur / Surguja | F43: 137 | G43: 137 | H43: 16797732 | I43: GEM/2026/B/7219163 | J43: proposal for hiring of tippers for transportation of 63000 tes of g 7 grade coal from ketki ug mine stock yard to mahan ii wharf wall siding of bhatgaon area via weigh bridge at.. | K43: Coal transport (RCR / siding) | L43: South Eastern Coalfields Limited | M43: Chhattisgarh | N43: Surguja | O43: 46079 | P43: AOC | Q43: M/S Chandan Kumar Singh | R43: G K Associates, Chandan Kumar Singh | S43: 5 named / 6 | T43: 1.21 | U43: =IF(ISNUMBER(G43),MAX(MAX(G43,Settings!$B$13)*Settings!$B$7*Settings!$B$5,IF(ISNUMBER(Settings!$B$12),Settings!$B$12,0))*(1+IF(Settings!$B$11="Y",0,Settings!$B$10/100))+N(Settings!$B$9),"") | W43: =IF(ISNUMBER(V43),IF(V43*Settings!$B$8>1000,"beyond table",IFERROR(LOOKUP(V43*Settings!$B$8,'FOIS 145A'!$A$2:$A$22,'FOIS 145A'!$C$2:$C$22)*(1+IF(Settings!$B$11="Y",0,Settings!$B$10/100)),"")),"") | X43: =IF(AND(ISNUMBER(U43),ISNUMBER(W43)),U43+W43,"") | Y43: =Settings!$B$6
A44: Yes | B44: mine named in title; plant/siding named in title | C44: Ambikapur / Surguja | D44: 137 | E44: Ambikapur / Surguja | F44: 137 | G44: 137 | H44: 16845426 | I44: GEM/2026/B/7213819 | J44: proposal for hiring of pay loader and tippers for loading and transportation of 56000 te of coal from amera ocp to bishrampur wharf wall siding for 60 days at 934 te per day | K44: Coal transport (RCR / siding) | L44: South Eastern Coalfields Limited | M44: Chhattisgarh | N44: Surguja | O44: 46078 | P44: AOC | Q44: M/S Chandan Kumar Singh | R44: G K Associates, Chandan Kumar Singh | S44: 5 named / 5 | T44: 1.77 | U44: =IF(ISNUMBER(G44),MAX(MAX(G44,Settings!$B$13)*Settings!$B$7*Settings!$B$5,IF(ISNUMBER(Settings!$B$12),Settings!$B$12,0))*(1+IF(Settings!$B$11="Y",0,Settings!$B$10/100))+N(Settings!$B$9),"") | W44: =IF(ISNUMBER(V44),IF(V44*Settings!$B$8>1000,"beyond table",IFERROR(LOOKUP(V44*Settings!$B$8,'FOIS 145A'!$A$2:$A$22,'FOIS 145A'!$C$2:$C$22)*(1+IF(Settings!$B$11="Y",0,Settings!$B$10/100)),"")),"") | X44: =IF(AND(ISNUMBER(U44),ISNUMBER(W44)),U44+W44,"") | Y44: =Settings!$B$6
A45: Yes | B45: mine named in title | C45: Ambikapur / Surguja | D45: 137 | G45: 137 | H45: 17262022 | I45: GEM/2026/B/7140468 | J45: wagon loading, loading and transportation of coal at amgaon ocp bishrampur area for 3650 days | K45: Coal transport (RCR / siding) | L45: South Eastern Coalfields Limited | M45: Chhattisgarh | N45: Surguja | O45: 46069 | P45: AOC | Q45: Surguja Bricks Industries | S45: 5 named / 17 | T45: 104.53 | U45: =IF(ISNUMBER(G45),MAX(MAX(G45,Settings!$B$13)*Settings!$B$7*Settings!$B$5,IF(ISNUMBER(Settings!$B$12),Settings!$B$12,0))*(1+IF(Settings!$B$11="Y",0,Settings!$B$10/100))+N(Settings!$B$9),"") | W45: =IF(ISNUMBER(V45),IF(V45*Settings!$B$8>1000,"beyond table",IFERROR(LOOKUP(V45*Settings!$B$8,'FOIS 145A'!$A$2:$A$22,'FOIS 145A'!$C$2:$C$22)*(1+IF(Settings!$B$11="Y",0,Settings!$B$10/100)),"")),"") | X45: =IF(AND(ISNUMBER(U45),ISNUMBER(W45)),U45+W45,"") | Y45: =Settings!$B$6
A46: Yes | B46: mine named in title; plant/siding named in title | C46: Ambikapur / Surguja | D46: 137 | E46: Ambikapur / Surguja | F46: 137 | G46: 137 | H46: 17281416 | I46: GEM/2026/B/7106097 | J46: transportaion of coal from ketki ug mine to mahan 2 and jainagar siding for period of 270 and 4648 days respectively | K46: Coal transport (RCR / siding) | L46: South Eastern Coalfields Limited | M46: Chhattisgarh | N46: Surguja | O46: 46051 | P46: AOC | Q46: Narendra Singh Bindra | S46: 5 named / 12 | T46: 70.66 | U46: =IF(ISNUMBER(G46),MAX(MAX(G46,Settings!$B$13)*Settings!$B$7*Settings!$B$5,IF(ISNUMBER(Settings!$B$12),Settings!$B$12,0))*(1+IF(Settings!$B$11="Y",0,Settings!$B$10/100))+N(Settings!$B$9),"") | W46: =IF(ISNUMBER(V46),IF(V46*Settings!$B$8>1000,"beyond table",IFERROR(LOOKUP(V46*Settings!$B$8,'FOIS 145A'!$A$2:$A$22,'FOIS 145A'!$C$2:$C$22)*(1+IF(Settings!$B$11="Y",0,Settings!$B$10/100)),"")),"") | X46: =IF(AND(ISNUMBER(U46),ISNUMBER(W46)),U46+W46,"") | Y46: =Settings!$B$6
A47: Yes | B47: mine named in title | C47: Ambikapur / Surguja | D47: 137 | G47: 137 | H47: 18266289 | I47: GEM/2026/B/7685060 | J47: loading and transportation of coal at amera ocp | K47: Coal transport (road) | L47: South Eastern Coalfields Limited | M47: Chhattisgarh | N47: Surguja | O47: 46209 | P47: AOC | Q47: Sri Constructions | S47: 5 named / 21 | T47: 139.96 | U47: =IF(ISNUMBER(G47),MAX(MAX(G47,Settings!$B$13)*Settings!$B$7*Settings!$B$5,IF(ISNUMBER(Settings!$B$12),Settings!$B$12,0))*(1+IF(Settings!$B$11="Y",0,Settings!$B$10/100))+N(Settings!$B$9),"") | W47: =IF(ISNUMBER(V47),IF(V47*Settings!$B$8>1000,"beyond table",IFERROR(LOOKUP(V47*Settings!$B$8,'FOIS 145A'!$A$2:$A$22,'FOIS 145A'!$C$2:$C$22)*(1+IF(Settings!$B$11="Y",0,Settings!$B$10/100)),"")),"") | X47: =IF(AND(ISNUMBER(U47),ISNUMBER(W47)),U47+W47,"") | Y47: =Settings!$B$6
A48: Yes | B48: mine = coal company's tender city; siding = same area | C48: Ambikapur / Surguja (tender city) | D48: 137 | E48: Ambikapur / Surguja (tender city) | F48: 137 | G48: 137 | H48: 17829018 | I48: GEM/2026/B/7685720 | J48: handling service, transport service, handling & transport service, hiring of payloader and tippers for loading and transportation of 230000 te of -100mm coal for a period of 120.. | K48: Coal transport (road) | L48: South Eastern Coalfields Limited | M48: Chhattisgarh | N48: Surguja | O48: 46209 | P48: AOC | Q48: M/S Chandan Kumar Singh | R48: Chandan Kumar Singh | S48: 5 named / 6 | T48: 7.39 | U48: =IF(ISNUMBER(G48),MAX(MAX(G48,Settings!$B$13)*Settings!$B$7*Settings!$B$5,IF(ISNUMBER(Settings!$B$12),Settings!$B$12,0))*(1+IF(Settings!$B$11="Y",0,Settings!$B$10/100))+N(Settings!$B$9),"") | W48: =IF(ISNUMBER(V48),IF(V48*Settings!$B$8>1000,"beyond table",IFERROR(LOOKUP(V48*Settings!$B$8,'FOIS 145A'!$A$2:$A$22,'FOIS 145A'!$C$2:$C$22)*(1+IF(Settings!$B$11="Y",0,Settings!$B$10/100)),"")),"") | X48: =IF(AND(ISNUMBER(U48),ISNUMBER(W48)),U48+W48,"") | Y48: =Settings!$B$6
A49: Yes | B49: mine named in title | C49: Ambikapur / Surguja | D49: 137 | G49: 137 | H49: 16845462 | I49: GEM/2026/B/7219625 | J49: proposal for hiring of a pay loader for mechanical loading of coal into tippers at coal stock yard amgaon ocp for 85000 te less than 100 mm and b transportation of coal .. | K49: Coal transport (road) | L49: South Eastern Coalfields Limited | M49: Chhattisgarh | N49: Surguja | O49: 46079 | P49: AOC | Q49: Om Logistics | R49: Chandan Kumar Singh | S49: 5 named / 5 | T49: 1.41 | U49: =IF(ISNUMBER(G49),MAX(MAX(G49,Settings!$B$13)*Settings!$B$7*Settings!$B$5,IF(ISNUMBER(Settings!$B$12),Settings!$B$12,0))*(1+IF(Settings!$B$11="Y",0,Settings!$B$10/100))+N(Settings!$B$9),"") | W49: =IF(ISNUMBER(V49),IF(V49*Settings!$B$8>1000,"beyond table",IFERROR(LOOKUP(V49*Settings!$B$8,'FOIS 145A'!$A$2:$A$22,'FOIS 145A'!$C$2:$C$22)*(1+IF(Settings!$B$11="Y",0,Settings!$B$10/100)),"")),"") | X49: =IF(AND(ISNUMBER(U49),ISNUMBER(W49)),U49+W49,"") | Y49: =Settings!$B$6
A50: Yes | B50: mine named in title; plant/siding named in title | C50: Ambikapur / Surguja | D50: 137 | E50: Ambikapur / Surguja | F50: 137 | G50: 137 | H50: 15478921 | I50: GEM/2025/B/6719300 | J50: transportation of 63000 te and 340 te of g7 grade coal from ketki ug mine stock yard to bhatgaon area destinations through hired tippers via weighbridges within 41 to 43 km lead | K50: Coal transport (road) | L50: South Eastern Coalfields Limited | M50: Chhattisgarh | N50: Surguja | O50: 45939 | P50: AOC | Q50: Narendra Singh Bindra | R50: G K Associates, Chandan Kumar Singh | S50: 5 named / 7 | T50: 1.35 | U50: =IF(ISNUMBER(G50),MAX(MAX(G50,Settings!$B$13)*Settings!$B$7*Settings!$B$5,IF(ISNUMBER(Settings!$B$12),Settings!$B$12,0))*(1+IF(Settings!$B$11="Y",0,Settings!$B$10/100))+N(Settings!$B$9),"") | W50: =IF(ISNUMBER(V50),IF(V50*Settings!$B$8>1000,"beyond table",IFERROR(LOOKUP(V50*Settings!$B$8,'FOIS 145A'!$A$2:$A$22,'FOIS 145A'!$C$2:$C$22)*(1+IF(Settings!$B$11="Y",0,Settings!$B$10/100)),"")),"") | X50: =IF(AND(ISNUMBER(U50),ISNUMBER(W50)),U50+W50,"") | Y50: =Settings!$B$6
A51: Yes | B51: plant/siding named in title | E51: Ambikapur / Surguja | F51: 137 | G51: 137 | H51: 14267063 | I51: 2025_BHEL_49216_1 | J51: point to point transport contract for transportation of coal bunker items assembly from bhel hpvp to mahan singrauli | K51: Coal transport (road) | L51: Bharat Heavy Electricals Limited | M51: Madhya Pradesh | N51: Singrauli | O51: 45819 | P51: Technical | Q51: - | S51: 5 named / 7 | U51: =IF(ISNUMBER(G51),MAX(MAX(G51,Settings!$B$13)*Settings!$B$7*Settings!$B$5,IF(ISNUMBER(Settings!$B$12),Settings!$B$12,0))*(1+IF(Settings!$B$11="Y",0,Settings!$B$10/100))+N(Settings!$B$9),"") | W51: =IF(ISNUMBER(V51),IF(V51*Settings!$B$8>1000,"beyond table",IFERROR(LOOKUP(V51*Settings!$B$8,'FOIS 145A'!$A$2:$A$22,'FOIS 145A'!$C$2:$C$22)*(1+IF(Settings!$B$11="Y",0,Settings!$B$10/100)),"")),"") | X51: =IF(AND(ISNUMBER(U51),ISNUMBER(W51)),U51+W51,"") | Y51: =Settings!$B$6
A52: Yes | B52: mine = coal company's tender city; siding = same area | C52: Ambikapur / Surguja (tender city) | D52: 137 | E52: Ambikapur / Surguja (tender city) | F52: 137 | G52: 137 | H52: 16716663 | I52: GEM/2026/B/7201133 | J52: proposal for hiring of pay loader with weight sensor for mechanical transfer of 2000000 te coal into railway wagons at bishrampur wharf wall siding including allied loading acti.. | K52: Loading / handling / crushing | L52: South Eastern Coalfields Limited | M52: Chhattisgarh | N52: Surguja | O52: 46076 | P52: AOC | Q52: Orbit Carriers Private Limited | R52: Chandan Kumar Singh | S52: 4 named / 4 | T52: 1.79 | U52: =IF(ISNUMBER(G52),MAX(MAX(G52,Settings!$B$13)*Settings!$B$7*Settings!$B$5,IF(ISNUMBER(Settings!$B$12),Settings!$B$12,0))*(1+IF(Settings!$B$11="Y",0,Settings!$B$10/100))+N(Settings!$B$9),"") | W52: =IF(ISNUMBER(V52),IF(V52*Settings!$B$8>1000,"beyond table",IFERROR(LOOKUP(V52*Settings!$B$8,'FOIS 145A'!$A$2:$A$22,'FOIS 145A'!$C$2:$C$22)*(1+IF(Settings!$B$11="Y",0,Settings!$B$10/100)),"")),"") | X52: =IF(AND(ISNUMBER(U52),ISNUMBER(W52)),U52+W52,"") | Y52: =Settings!$B$6
A53: Yes | B53: mine named in title | C53: Ambikapur / Surguja | D53: 137 | G53: 137 | H53: 17681972 | I53: GEM/2026/B/7325071 | J53: hiring of hemms for loading and transportaion of coal at gayatri ug mine of bishrampur area secl for 2190 days | K53: Mining services (OB / extraction) | L53: South Eastern Coalfields Limited | M53: Chhattisgarh | N53: Surguja | O53: 46104 | P53: AOC | Q53: M/S Chandan Kumar Singh | S53: 5 named / 18 | T53: 50.29 | U53: =IF(ISNUMBER(G53),MAX(MAX(G53,Settings!$B$13)*Settings!$B$7*Settings!$B$5,IF(ISNUMBER(Settings!$B$12),Settings!$B$12,0))*(1+IF(Settings!$B$11="Y",0,Settings!$B$10/100))+N(Settings!$B$9),"") | W53: =IF(ISNUMBER(V53),IF(V53*Settings!$B$8>1000,"beyond table",IFERROR(LOOKUP(V53*Settings!$B$8,'FOIS 145A'!$A$2:$A$22,'FOIS 145A'!$C$2:$C$22)*(1+IF(Settings!$B$11="Y",0,Settings!$B$10/100)),"")),"") | X53: =IF(AND(ISNUMBER(U53),ISNUMBER(W53)),U53+W53,"") | Y53: =Settings!$B$6
A54: Yes | B54: mine named in title | C54: Ambikapur / Surguja | D54: 137 | G54: 137 | H54: 15763453 | I54: GEM/2025/B/6862935 | J54: hiring of crawler mounted drill machine 159 mm dia with wet drilling for 5763 m coal holes at forest patch for 30 days at amgaon ocp secl bishrampur area | K54: Other | L54: South Eastern Coalfields Limited | M54: Chhattisgarh | N54: Surguja | O54: 45983 | P54: AOC | Q54: G K Associates | R54: G K Associates | S54: 1 named / 1 | T54: 0.1 | U54: =IF(ISNUMBER(G54),MAX(MAX(G54,Settings!$B$13)*Settings!$B$7*Settings!$B$5,IF(ISNUMBER(Settings!$B$12),Settings!$B$12,0))*(1+IF(Settings!$B$11="Y",0,Settings!$B$10/100))+N(Settings!$B$9),"") | W54: =IF(ISNUMBER(V54),IF(V54*Settings!$B$8>1000,"beyond table",IFERROR(LOOKUP(V54*Settings!$B$8,'FOIS 145A'!$A$2:$A$22,'FOIS 145A'!$C$2:$C$22)*(1+IF(Settings!$B$11="Y",0,Settings!$B$10/100)),"")),"") | X54: =IF(AND(ISNUMBER(U54),ISNUMBER(W54)),U54+W54,"") | Y54: =Settings!$B$6
A55: Yes | B55: plant/siding named in title; mine = coal company's tender city | C55: Ambikapur / Surguja (tender city) | D55: 137 | E55: Ambikapur / Surguja | F55: 137 | G55: 137 | H55: 15692582 | I55: GEM/2025/B/6674746 | J55: hiring of pay loder incorporated with weight sensors for mechanical transfer of size 100 mm coal to railway wagons for a quantity of 5891332 te for 1095 days at mahan ii wharf.. | K55: Other | L55: South Eastern Coalfields Limited | M55: Chhattisgarh | N55: Surguja | O55: 45929 | P55: AOC | Q55: Surguja Bricks Industries | R55: G K Associates, Chandan Kumar Singh | S55: 5 named / 9 | T55: 5.18 | U55: =IF(ISNUMBER(G55),MAX(MAX(G55,Settings!$B$13)*Settings!$B$7*Settings!$B$5,IF(ISNUMBER(Settings!$B$12),Settings!$B$12,0))*(1+IF(Settings!$B$11="Y",0,Settings!$B$10/100))+N(Settings!$B$9),"") | W55: =IF(ISNUMBER(V55),IF(V55*Settings!$B$8>1000,"beyond table",IFERROR(LOOKUP(V55*Settings!$B$8,'FOIS 145A'!$A$2:$A$22,'FOIS 145A'!$C$2:$C$22)*(1+IF(Settings!$B$11="Y",0,Settings!$B$10/100)),"")),"") | X55: =IF(AND(ISNUMBER(U55),ISNUMBER(W55)),U55+W55,"") | Y55: =Settings!$B$6
A56: Borderline | B56: plant = tender city | E56: Rourkela (tender city) | F56: 156 | G56: 156 | H56: 18282487 | I56: GEM/2026/B/7469992 | J56: lifting of of coal from mcl mines (kuldabelpaharlajkuralakhanpursamaleswerigarjanbaha l) to any railway sidinggoods shed private siding ( ser,secr,east coast railways) under rcr mode & supervison of c | K56: Coal transport (RCR / siding) | L56: Ntpc-Sail Power Company Private Limited | M56: Orissa | N56: Rourkela | O56: 46206 | P56: Financial | Q56: - | R56: Anoop Road Carriers, Bharat Road Carrier | S56: 5 named / 12 | U56: =IF(ISNUMBER(G56),MAX(MAX(G56,Settings!$B$13)*Settings!$B$7*Settings!$B$5,IF(ISNUMBER(Settings!$B$12),Settings!$B$12,0))*(1+IF(Settings!$B$11="Y",0,Settings!$B$10/100))+N(Settings!$B$9),"") | W56: =IF(ISNUMBER(V56),IF(V56*Settings!$B$8>1000,"beyond table",IFERROR(LOOKUP(V56*Settings!$B$8,'FOIS 145A'!$A$2:$A$22,'FOIS 145A'!$C$2:$C$22)*(1+IF(Settings!$B$11="Y",0,Settings!$B$10/100)),"")),"") | X56: =IF(AND(ISNUMBER(U56),ISNUMBER(W56)),U56+W56,"") | Y56: =Settings!$B$6
A57: Borderline | B57: plant/siding named in title | E57: Rourkela | F57: 156 | G57: 156 | H57: 16080231 | I57: GEM/2025/B/7016181 | J57: short term one time coal shifting from dsp beds to nspcl coal yard,pp-ii and pp-iii | K57: Loading / handling / crushing | L57: Ntpc-Sail Power Company Private Limited | M57: West Bengal | N57: Durgapur | O57: 46020 | P57: Financial | Q57: - | R57: United Coal Carriers | S57: 5 named / 6 | U57: =IF(ISNUMBER(G57),MAX(MAX(G57,Settings!$B$13)*Settings!$B$7*Settings!$B$5,IF(ISNUMBER(Settings!$B$12),Settings!$B$12,0))*(1+IF(Settings!$B$11="Y",0,Settings!$B$10/100))+N(Settings!$B$9),"") | W57: =IF(ISNUMBER(V57),IF(V57*Settings!$B$8>1000,"beyond table",IFERROR(LOOKUP(V57*Settings!$B$8,'FOIS 145A'!$A$2:$A$22,'FOIS 145A'!$C$2:$C$22)*(1+IF(Settings!$B$11="Y",0,Settings!$B$10/100)),"")),"") | X57: =IF(AND(ISNUMBER(U57),ISNUMBER(W57)),U57+W57,"") | Y57: =Settings!$B$6
A58: Borderline | B58: plant/siding named in title | E58: Rourkela | F58: 156 | G58: 156 | H58: 13548763 | I58: GEM/2025/B/6130476 | J58: coal shifting from dsp beds to nspcl coal yard of chp pp-ii and iii(ssc/2 | K58: Loading / handling / crushing | L58: Ntpc-Sail Power Company Private Limited | M58: West Bengal | N58: Durgapur | O58: 45792 | P58: AOC | Q58: Phoenix Solutions | R58: Nkas Services | S58: 5 named / 5 | T58: 1.63 | U58: =IF(ISNUMBER(G58),MAX(MAX(G58,Settings!$B$13)*Settings!$B$7*Settings!$B$5,IF(ISNUMBER(Settings!$B$12),Settings!$B$12,0))*(1+IF(Settings!$B$11="Y",0,Settings!$B$10/100))+N(Settings!$B$9),"") | W58: =IF(ISNUMBER(V58),IF(V58*Settings!$B$8>1000,"beyond table",IFERROR(LOOKUP(V58*Settings!$B$8,'FOIS 145A'!$A$2:$A$22,'FOIS 145A'!$C$2:$C$22)*(1+IF(Settings!$B$11="Y",0,Settings!$B$10/100)),"")),"") | X58: =IF(AND(ISNUMBER(U58),ISNUMBER(W58)),U58+W58,"") | Y58: =Settings!$B$6
A59: Borderline | B59: plant/siding named in title | E59: Rourkela | F59: 156 | G59: 156 | H59: 12298393 | I59: GEM/2024/B/5717697 | J59: coal shifting from dsp beds to nspcl coal yard of chp ppii and iii for 3 | K59: Loading / handling / crushing | L59: Ntpc-Sail Power Company Private Limited | M59: West Bengal | N59: Durgapur | O59: 45658 | P59: AOC | Q59: M/S United Coal Carriers | R59: United Coal Carriers | S59: 4 named / 4 | T59: 0.85 | U59: =IF(ISNUMBER(G59),MAX(MAX(G59,Settings!$B$13)*Settings!$B$7*Settings!$B$5,IF(ISNUMBER(Settings!$B$12),Settings!$B$12,0))*(1+IF(Settings!$B$11="Y",0,Settings!$B$10/100))+N(Settings!$B$9),"") | W59: =IF(ISNUMBER(V59),IF(V59*Settings!$B$8>1000,"beyond table",IFERROR(LOOKUP(V59*Settings!$B$8,'FOIS 145A'!$A$2:$A$22,'FOIS 145A'!$C$2:$C$22)*(1+IF(Settings!$B$11="Y",0,Settings!$B$10/100)),"")),"") | X59: =IF(AND(ISNUMBER(U59),ISNUMBER(W59)),U59+W59,"") | Y59: =Settings!$B$6
A60: Borderline | B60: mine named in title | C60: Baikunthpur / Chirimiri (Korea) | D60: 174 | G60: 174 | H60: 17026374 | I60: GEM/2026/B/7088635 | J60: handling service, handling & transport service, transport service, hiring of tippers for transportation of coal and loading of coal at ncph r6 mine at chirimiri area | K60: Coal transport (road) | L60: South Eastern Coalfields Limited | M60: Chhattisgarh | N60: Korea | O60: 46046 | P60: AOC | Q60: Nakul Tiwari | R60: G K Associates, Chandan Kumar Singh | S60: 5 named / 6 | T60: 7.23 | U60: =IF(ISNUMBER(G60),MAX(MAX(G60,Settings!$B$13)*Settings!$B$7*Settings!$B$5,IF(ISNUMBER(Settings!$B$12),Settings!$B$12,0))*(1+IF(Settings!$B$11="Y",0,Settings!$B$10/100))+N(Settings!$B$9),"") | W60: =IF(ISNUMBER(V60),IF(V60*Settings!$B$8>1000,"beyond table",IFERROR(LOOKUP(V60*Settings!$B$8,'FOIS 145A'!$A$2:$A$22,'FOIS 145A'!$C$2:$C$22)*(1+IF(Settings!$B$11="Y",0,Settings!$B$10/100)),"")),"") | X60: =IF(AND(ISNUMBER(U60),ISNUMBER(W60)),U60+W60,"") | Y60: =Settings!$B$6
A61: Borderline | B61: mine = coal company's tender city; siding = same area | C61: Baikunthpur / Chirimiri (Korea) (tender city) | D61: 174 | E61: Baikunthpur / Chirimiri (Korea) (tender city) | F61: 174 | G61: 174 | H61: 14761654 | I61: GEM/2025/B/6531525 | J61: coal transportation from k | K61: Coal transport (road) | L61: South Eastern Coalfields Limited | M61: Chhattisgarh | N61: Korea | O61: 45883 | P61: AOC | Q61: Ajay Shrivas | S61: 3 named / 3 | T61: 0.41 | U61: =IF(ISNUMBER(G61),MAX(MAX(G61,Settings!$B$13)*Settings!$B$7*Settings!$B$5,IF(ISNUMBER(Settings!$B$12),Settings!$B$12,0))*(1+IF(Settings!$B$11="Y",0,Settings!$B$10/100))+N(Settings!$B$9),"") | W61: =IF(ISNUMBER(V61),IF(V61*Settings!$B$8>1000,"beyond table",IFERROR(LOOKUP(V61*Settings!$B$8,'FOIS 145A'!$A$2:$A$22,'FOIS 145A'!$C$2:$C$22)*(1+IF(Settings!$B$11="Y",0,Settings!$B$10/100)),"")),"") | X61: =IF(AND(ISNUMBER(U61),ISNUMBER(W61)),U61+W61,"") | Y61: =Settings!$B$6
A62: Borderline | B62: mine named in title | C62: Baikunthpur / Chirimiri (Korea) | D62: 174 | G62: 174 | H62: 14370610 | I62: GEM/2025/B/6354284 | J62: handling ,transport and other mining services - percentagequote based - handling & transport service, loading andtransportation of coal at rani atari chirimiri area | K62: Coal transport (road) | L62: South Eastern Coalfields Limited | M62: Chhattisgarh | N62: Korea | O62: 45845 | P62: AOC | Q62: G K Associates | S62: 5 named / 29 | T62: 81.11 | U62: =IF(ISNUMBER(G62),MAX(MAX(G62,Settings!$B$13)*Settings!$B$7*Settings!$B$5,IF(ISNUMBER(Settings!$B$12),Settings!$B$12,0))*(1+IF(Settings!$B$11="Y",0,Settings!$B$10/100))+N(Settings!$B$9),"") | W62: =IF(ISNUMBER(V62),IF(V62*Settings!$B$8>1000,"beyond table",IFERROR(LOOKUP(V62*Settings!$B$8,'FOIS 145A'!$A$2:$A$22,'FOIS 145A'!$C$2:$C$22)*(1+IF(Settings!$B$11="Y",0,Settings!$B$10/100)),"")),"") | X62: =IF(AND(ISNUMBER(U62),ISNUMBER(W62)),U62+W62,"") | Y62: =Settings!$B$6
A63: Borderline | B63: mine = coal company's tender city; siding = same area | C63: Baikunthpur / Chirimiri (Korea) (tender city) | D63: 174 | E63: Baikunthpur / Chirimiri (Korea) (tender city) | F63: 174 | G63: 174 | H63: 13712378 | I63: GEM/2025/B/6218223 | J63: handling & transport servi | K63: Coal transport (road) | L63: South Eastern Coalfields Limited | M63: Chhattisgarh | N63: Korea | O63: 45803 | P63: AOC | Q63: Dadan Singh Llp | R63: G K Associates, Chandan Kumar Singh | S63: 5 named / 7 | T63: 7.05 | U63: =IF(ISNUMBER(G63),MAX(MAX(G63,Settings!$B$13)*Settings!$B$7*Settings!$B$5,IF(ISNUMBER(Settings!$B$12),Settings!$B$12,0))*(1+IF(Settings!$B$11="Y",0,Settings!$B$10/100))+N(Settings!$B$9),"") | W63: =IF(ISNUMBER(V63),IF(V63*Settings!$B$8>1000,"beyond table",IFERROR(LOOKUP(V63*Settings!$B$8,'FOIS 145A'!$A$2:$A$22,'FOIS 145A'!$C$2:$C$22)*(1+IF(Settings!$B$11="Y",0,Settings!$B$10/100)),"")),"") | X63: =IF(AND(ISNUMBER(U63),ISNUMBER(W63)),U63+W63,"") | Y63: =Settings!$B$6
A64: Borderline | B64: mine = coal company's tender city; siding = same area | C64: Baikunthpur / Chirimiri (Korea) (tender city) | D64: 174 | E64: Baikunthpur / Chirimiri (Korea) (tender city) | F64: 174 | G64: 174 | H64: 13609214 | I64: GEM/2025/B/6201579 | J64: loading and transportation | K64: Coal transport (road) | L64: South Eastern Coalfields Limited | M64: Chhattisgarh | N64: Korea | O64: 45798 | P64: AOC | Q64: M/S Ramesh Kumar Agrawal And Sons | R64: G K Associates | S64: 5 named / 10 | T64: 7 | U64: =IF(ISNUMBER(G64),MAX(MAX(G64,Settings!$B$13)*Settings!$B$7*Settings!$B$5,IF(ISNUMBER(Settings!$B$12),Settings!$B$12,0))*(1+IF(Settings!$B$11="Y",0,Settings!$B$10/100))+N(Settings!$B$9),"") | W64: =IF(ISNUMBER(V64),IF(V64*Settings!$B$8>1000,"beyond table",IFERROR(LOOKUP(V64*Settings!$B$8,'FOIS 145A'!$A$2:$A$22,'FOIS 145A'!$C$2:$C$22)*(1+IF(Settings!$B$11="Y",0,Settings!$B$10/100)),"")),"") | X64: =IF(AND(ISNUMBER(U64),ISNUMBER(W64)),U64+W64,"") | Y64: =Settings!$B$6
A65: Borderline | B65: mine = coal company's tender city; siding = same area | C65: Baikunthpur / Chirimiri (Korea) (tender city) | D65: 174 | E65: Baikunthpur / Chirimiri (Korea) (tender city) | F65: 174 | G65: 174 | H65: 13485534 | I65: GEM/2025/B/6155880 | J65: handling & transport servi | K65: Coal transport (road) | L65: South Eastern Coalfields Limited | M65: Chhattisgarh | N65: Korea | O65: 45784 | P65: AOC | Q65: M/S Chandan Kumar Singh | S65: 5 named / 8 | T65: 5.33 | U65: =IF(ISNUMBER(G65),MAX(MAX(G65,Settings!$B$13)*Settings!$B$7*Settings!$B$5,IF(ISNUMBER(Settings!$B$12),Settings!$B$12,0))*(1+IF(Settings!$B$11="Y",0,Settings!$B$10/100))+N(Settings!$B$9),"") | W65: =IF(ISNUMBER(V65),IF(V65*Settings!$B$8>1000,"beyond table",IFERROR(LOOKUP(V65*Settings!$B$8,'FOIS 145A'!$A$2:$A$22,'FOIS 145A'!$C$2:$C$22)*(1+IF(Settings!$B$11="Y",0,Settings!$B$10/100)),"")),"") | X65: =IF(AND(ISNUMBER(U65),ISNUMBER(W65)),U65+W65,"") | Y65: =Settings!$B$6
A66: Borderline | B66: mine = coal company's tender city; siding = same area | C66: Baikunthpur / Chirimiri (Korea) (tender city) | D66: 174 | E66: Baikunthpur / Chirimiri (Korea) (tender city) | F66: 174 | G66: 174 | H66: 13513655 | I66: GEM/2025/B/6174810 | J66: coal transportation from k | K66: Coal transport (road) | L66: South Eastern Coalfields Limited | M66: Chhattisgarh | N66: Korea | O66: 45783 | P66: AOC | Q66: Harsh Roadlines Private Limited | S66: 4 named / 4 | T66: 0.41 | U66: =IF(ISNUMBER(G66),MAX(MAX(G66,Settings!$B$13)*Settings!$B$7*Settings!$B$5,IF(ISNUMBER(Settings!$B$12),Settings!$B$12,0))*(1+IF(Settings!$B$11="Y",0,Settings!$B$10/100))+N(Settings!$B$9),"") | W66: =IF(ISNUMBER(V66),IF(V66*Settings!$B$8>1000,"beyond table",IFERROR(LOOKUP(V66*Settings!$B$8,'FOIS 145A'!$A$2:$A$22,'FOIS 145A'!$C$2:$C$22)*(1+IF(Settings!$B$11="Y",0,Settings!$B$10/100)),"")),"") | X66: =IF(AND(ISNUMBER(U66),ISNUMBER(W66)),U66+W66,"") | Y66: =Settings!$B$6
A67: Borderline | B67: mine = coal company's tender city; siding = same area | C67: Baikunthpur / Chirimiri (Korea) (tender city) | D67: 174 | E67: Baikunthpur / Chirimiri (Korea) (tender city) | F67: 174 | G67: 174 | H67: 13180185 | I67: GEM/2025/B/6070928 | J67: hiring of payloader for lo | K67: Other | L67: South Eastern Coalfields Limited | M67: Chhattisgarh | N67: Korea | O67: 45751 | P67: AOC | Q67: G K Associates | R67: G K Associates | S67: 5 named / 14 | T67: 37.74 | U67: =IF(ISNUMBER(G67),MAX(MAX(G67,Settings!$B$13)*Settings!$B$7*Settings!$B$5,IF(ISNUMBER(Settings!$B$12),Settings!$B$12,0))*(1+IF(Settings!$B$11="Y",0,Settings!$B$10/100))+N(Settings!$B$9),"") | W67: =IF(ISNUMBER(V67),IF(V67*Settings!$B$8>1000,"beyond table",IFERROR(LOOKUP(V67*Settings!$B$8,'FOIS 145A'!$A$2:$A$22,'FOIS 145A'!$C$2:$C$22)*(1+IF(Settings!$B$11="Y",0,Settings!$B$10/100)),"")),"") | X67: =IF(AND(ISNUMBER(U67),ISNUMBER(W67)),U67+W67,"") | Y67: =Settings!$B$6
A68: Borderline | B68: mine = coal company's tender city; siding = same area | C68: Baikunthpur / Chirimiri (Korea) (tender city) | D68: 174 | E68: Baikunthpur / Chirimiri (Korea) (tender city) | F68: 174 | G68: 174 | H68: 13097848 | I68: GEM/2025/B/6038225 | J68: hiring of pay loader for l | K68: Other | L68: South Eastern Coalfields Limited | M68: Chhattisgarh | N68: Korea | O68: 45740 | P68: AOC | Q68: G K Associates, M/S Ramesh Kumar Agrawal And Sons, Vivek Construction | R68: G K Associates | S68: 5 named / 17 | T68: 25.16 | U68: =IF(ISNUMBER(G68),MAX(MAX(G68,Settings!$B$13)*Settings!$B$7*Settings!$B$5,IF(ISNUMBER(Settings!$B$12),Settings!$B$12,0))*(1+IF(Settings!$B$11="Y",0,Settings!$B$10/100))+N(Settings!$B$9),"") | W68: =IF(ISNUMBER(V68),IF(V68*Settings!$B$8>1000,"beyond table",IFERROR(LOOKUP(V68*Settings!$B$8,'FOIS 145A'!$A$2:$A$22,'FOIS 145A'!$C$2:$C$22)*(1+IF(Settings!$B$11="Y",0,Settings!$B$10/100)),"")),"") | X68: =IF(AND(ISNUMBER(U68),ISNUMBER(W68)),U68+W68,"") | Y68: =Settings!$B$6
A69: Unknown | B69: mine named in title | C69: Talcher / Angul | D69: 217 | G69: 217 | H69: 17648465 | I69: GEM/2026/B/7395324 | J69: loading and transportation of coal from stock yards of ananta ocp jagannath area to siding lmgti and lmgtii of lingraj area mcl | K69: Coal transport (RCR / siding) | L69: Mahanadi Coalfields Limited | M69: Orissa | N69: Angul | O69: 46125 | P69: Financial | Q69: - | R69: Saikrupa Coal Supplier | S69: 5 named / 8 | U69: =IF(ISNUMBER(G69),MAX(MAX(G69,Settings!$B$13)*Settings!$B$7*Settings!$B$5,IF(ISNUMBER(Settings!$B$12),Settings!$B$12,0))*(1+IF(Settings!$B$11="Y",0,Settings!$B$10/100))+N(Settings!$B$9),"") | W69: =IF(ISNUMBER(V69),IF(V69*Settings!$B$8>1000,"beyond table",IFERROR(LOOKUP(V69*Settings!$B$8,'FOIS 145A'!$A$2:$A$22,'FOIS 145A'!$C$2:$C$22)*(1+IF(Settings!$B$11="Y",0,Settings!$B$10/100)),"")),"") | X69: =IF(AND(ISNUMBER(U69),ISNUMBER(W69)),U69+W69,"") | Y69: =Settings!$B$6
A70: Unknown | B70: plant = tender city | E70: Talcher / Angul (tender city) | F70: 217 | G70: 217 | H70: 17906545 | I70: GEM/2026/B/7405314 | J70: loading of yard coal into nalco wagons by pc-210 and pc-220 pay loader at foph siding and chp-3 extension stockyard | K70: Loading / handling / crushing | L70: National Aluminium Company Limited | M70: Orissa | N70: Angul | O70: 46149 | P70: AOC | Q70: M/S Govinda Enterprises | S70: 5 named / 11 | T70: 4 | U70: =IF(ISNUMBER(G70),MAX(MAX(G70,Settings!$B$13)*Settings!$B$7*Settings!$B$5,IF(ISNUMBER(Settings!$B$12),Settings!$B$12,0))*(1+IF(Settings!$B$11="Y",0,Settings!$B$10/100))+N(Settings!$B$9),"") | W70: =IF(ISNUMBER(V70),IF(V70*Settings!$B$8>1000,"beyond table",IFERROR(LOOKUP(V70*Settings!$B$8,'FOIS 145A'!$A$2:$A$22,'FOIS 145A'!$C$2:$C$22)*(1+IF(Settings!$B$11="Y",0,Settings!$B$10/100)),"")),"") | X70: =IF(AND(ISNUMBER(U70),ISNUMBER(W70)),U70+W70,"") | Y70: =Settings!$B$6
A71: Unknown | B71: plant = tender city | E71: Talcher / Angul (tender city) | F71: 217 | G71: 217 | H71: 17596798 | I71: GEM/2025/B/7004499 | J71: coordination liasion, loading, supervision and movement of coal rakes for linkage coal and e-auction coal supplied through railway bobrn rakes | K71: Loading / handling / crushing | L71: National Aluminium Company Limited | M71: Orissa | N71: Angul | O71: 46043 | P71: AOC | Q71: Coalsale Company Limited | R71: Anoop Road Carriers, Godavari Commodities | S71: 5 named / 10 | T71: 1.32 | U71: =IF(ISNUMBER(G71),MAX(MAX(G71,Settings!$B$13)*Settings!$B$7*Settings!$B$5,IF(ISNUMBER(Settings!$B$12),Settings!$B$12,0))*(1+IF(Settings!$B$11="Y",0,Settings!$B$10/100))+N(Settings!$B$9),"") | W71: =IF(ISNUMBER(V71),IF(V71*Settings!$B$8>1000,"beyond table",IFERROR(LOOKUP(V71*Settings!$B$8,'FOIS 145A'!$A$2:$A$22,'FOIS 145A'!$C$2:$C$22)*(1+IF(Settings!$B$11="Y",0,Settings!$B$10/100)),"")),"") | X71: =IF(AND(ISNUMBER(U71),ISNUMBER(W71)),U71+W71,"") | Y71: =Settings!$B$6
A72: Unknown | B72: plant = tender city | E72: Talcher / Angul (tender city) | F72: 217 | G72: 217 | H72: 15581027 | I72: GEM/2025/B/6475875 | J72: unloading of coal frombobrn wagon on track hoppers | K72: Loading / handling / crushing | L72: National Aluminium Company Limited | M72: Orissa | N72: Angul | O72: 45890 | P72: AOC | Q72: M/S Govinda Enterprises | S72: 5 named / 7 | T72: 0.95 | U72: =IF(ISNUMBER(G72),MAX(MAX(G72,Settings!$B$13)*Settings!$B$7*Settings!$B$5,IF(ISNUMBER(Settings!$B$12),Settings!$B$12,0))*(1+IF(Settings!$B$11="Y",0,Settings!$B$10/100))+N(Settings!$B$9),"") | W72: =IF(ISNUMBER(V72),IF(V72*Settings!$B$8>1000,"beyond table",IFERROR(LOOKUP(V72*Settings!$B$8,'FOIS 145A'!$A$2:$A$22,'FOIS 145A'!$C$2:$C$22)*(1+IF(Settings!$B$11="Y",0,Settings!$B$10/100)),"")),"") | X72: =IF(AND(ISNUMBER(U72),ISNUMBER(W72)),U72+W72,"") | Y72: =Settings!$B$6
A73: Unknown | B73: no location in title | H73: 18325913 | I73: GEM/2026/B/7928927 | J73: supply of - steam coal (q3) - | quantity - 11500 | K73: Coal supply | L73: Indian Rare Earths Limited | M73: Orissa | N73: Ganjam | O73: 46277 | P73: Financial | Q73: - | R73: Godavari Commodities, Mohit Minerals | S73: 5 named / 6 | U73: =IF(ISNUMBER(G73),MAX(MAX(G73,Settings!$B$13)*Settings!$B$7*Settings!$B$5,IF(ISNUMBER(Settings!$B$12),Settings!$B$12,0))*(1+IF(Settings!$B$11="Y",0,Settings!$B$10/100))+N(Settings!$B$9),"") | W73: =IF(ISNUMBER(V73),IF(V73*Settings!$B$8>1000,"beyond table",IFERROR(LOOKUP(V73*Settings!$B$8,'FOIS 145A'!$A$2:$A$22,'FOIS 145A'!$C$2:$C$22)*(1+IF(Settings!$B$11="Y",0,Settings!$B$10/100)),"")),"") | X73: =IF(AND(ISNUMBER(U73),ISNUMBER(W73)),U73+W73,"") | Y73: =Settings!$B$6
A74: Unknown | B74: no location in title | H74: 17284876 | I74: GEM/2026/B/7416658 | J74: supply of - steam coal (q3) - | quantity - 11500 | K74: Coal supply | L74: Indian Rare Earths Limited | M74: Orissa | N74: Ganjam | O74: 46142 | P74: Financial | Q74: - | R74: Godavari Commodities | S74: 5 named / 9 | U74: =IF(ISNUMBER(G74),MAX(MAX(G74,Settings!$B$13)*Settings!$B$7*Settings!$B$5,IF(ISNUMBER(Settings!$B$12),Settings!$B$12,0))*(1+IF(Settings!$B$11="Y",0,Settings!$B$10/100))+N(Settings!$B$9),"") | W74: =IF(ISNUMBER(V74),IF(V74*Settings!$B$8>1000,"beyond table",IFERROR(LOOKUP(V74*Settings!$B$8,'FOIS 145A'!$A$2:$A$22,'FOIS 145A'!$C$2:$C$22)*(1+IF(Settings!$B$11="Y",0,Settings!$B$10/100)),"")),"") | X74: =IF(AND(ISNUMBER(U74),ISNUMBER(W74)),U74+W74,"") | Y74: =Settings!$B$6
A75: Unknown | B75: no location in title | H75: 16020026 | I75: GEM/2025/B/6868675 | J75: supply of - steam coal (q3) - | quantity - 11500 | K75: Coal supply | L75: Indian Rare Earths Limited | M75: Orissa | N75: Ganjam | O75: 45994 | P75: Financial | Q75: - | R75: Godavari Commodities | S75: 5 named / 9 | U75: =IF(ISNUMBER(G75),MAX(MAX(G75,Settings!$B$13)*Settings!$B$7*Settings!$B$5,IF(ISNUMBER(Settings!$B$12),Settings!$B$12,0))*(1+IF(Settings!$B$11="Y",0,Settings!$B$10/100))+N(Settings!$B$9),"") | W75: =IF(ISNUMBER(V75),IF(V75*Settings!$B$8>1000,"beyond table",IFERROR(LOOKUP(V75*Settings!$B$8,'FOIS 145A'!$A$2:$A$22,'FOIS 145A'!$C$2:$C$22)*(1+IF(Settings!$B$11="Y",0,Settings!$B$10/100)),"")),"") | X75: =IF(AND(ISNUMBER(U75),ISNUMBER(W75)),U75+W75,"") | Y75: =Settings!$B$6
A76: Unknown | B76: no location in title | H76: 15112753 | I76: GEM/2025/B/6540145 | J76: supply of - steam coal (q3) | quantity - 11500 | K76: Coal supply | L76: Indian Rare Earths Limited | M76: Orissa | N76: Ganjam | O76: 45897 | P76: Financial | Q76: - | R76: Godavari Commodities | S76: 5 named / 8 | U76: =IF(ISNUMBER(G76),MAX(MAX(G76,Settings!$B$13)*Settings!$B$7*Settings!$B$5,IF(ISNUMBER(Settings!$B$12),Settings!$B$12,0))*(1+IF(Settings!$B$11="Y",0,Settings!$B$10/100))+N(Settings!$B$9),"") | W76: =IF(ISNUMBER(V76),IF(V76*Settings!$B$8>1000,"beyond table",IFERROR(LOOKUP(V76*Settings!$B$8,'FOIS 145A'!$A$2:$A$22,'FOIS 145A'!$C$2:$C$22)*(1+IF(Settings!$B$11="Y",0,Settings!$B$10/100)),"")),"") | X76: =IF(AND(ISNUMBER(U76),ISNUMBER(W76)),U76+W76,"") | Y76: =Settings!$B$6
A77: Unknown | B77: no location in title | H77: 14401813 | I77: 2025_OMFED_114495_1 | J77: supply of coal (g-12) | K77: Coal supply | L77: Orissa State Co-Operative Milk Producers Federation Limited | M77: Orissa | N77: Keonjhar | O77: 45845 | P77: AOC | Q77: M/S Sanjukta Mohanty | R77: Godavari Commodities | S77: 3 named / 3 | T77: 0 | U77: =IF(ISNUMBER(G77),MAX(MAX(G77,Settings!$B$13)*Settings!$B$7*Settings!$B$5,IF(ISNUMBER(Settings!$B$12),Settings!$B$12,0))*(1+IF(Settings!$B$11="Y",0,Settings!$B$10/100))+N(Settings!$B$9),"") | W77: =IF(ISNUMBER(V77),IF(V77*Settings!$B$8>1000,"beyond table",IFERROR(LOOKUP(V77*Settings!$B$8,'FOIS 145A'!$A$2:$A$22,'FOIS 145A'!$C$2:$C$22)*(1+IF(Settings!$B$11="Y",0,Settings!$B$10/100)),"")),"") | X77: =IF(AND(ISNUMBER(U77),ISNUMBER(W77)),U77+W77,"") | Y77: =Settings!$B$6
A78: Unknown | B78: no location in title | H78: 12546101 | I78: GEM/2025/B/5798333 | J78: steam coal,steam coal | K78: Coal supply | L78: Indian Rare Earths Limited | M78: Orissa | N78: Ganjam | O78: 45688 | P78: Financial | Q78: - | R78: Godavari Commodities, Sangita Sales | S78: 5 named / 7 | U78: =IF(ISNUMBER(G78),MAX(MAX(G78,Settings!$B$13)*Settings!$B$7*Settings!$B$5,IF(ISNUMBER(Settings!$B$12),Settings!$B$12,0))*(1+IF(Settings!$B$11="Y",0,Settings!$B$10/100))+N(Settings!$B$9),"") | W78: =IF(ISNUMBER(V78),IF(V78*Settings!$B$8>1000,"beyond table",IFERROR(LOOKUP(V78*Settings!$B$8,'FOIS 145A'!$A$2:$A$22,'FOIS 145A'!$C$2:$C$22)*(1+IF(Settings!$B$11="Y",0,Settings!$B$10/100)),"")),"") | X78: =IF(AND(ISNUMBER(U78),ISNUMBER(W78)),U78+W78,"") | Y78: =Settings!$B$6
A79: Unknown | B79: no location in title | H79: 18306348 | I79: 2026_NTPC_112044_1 | J79: transportation of 200000 mt of coal from mcl mines (int. lbl) to ntpc - transportation of 200000 mt of coal from mcl mines (int. lbl) to ntpcsolapur via rcr mode | K79: Coal transport (RCR / siding) | L79: National Thermal Power Corporation Limited | M79: Chhattisgarh | N79: Raipur | O79: 46290 | P79: AOC | Q79: Bharat Road Carrier Private Limited | R79: Anoop Road Carriers, Bharat Road Carrier, Sangita Sales, Swami Fuels | S79: 5 named / 6 | T79: 7.84 | U79: =IF(ISNUMBER(G79),MAX(MAX(G79,Settings!$B$13)*Settings!$B$7*Settings!$B$5,IF(ISNUMBER(Settings!$B$12),Settings!$B$12,0))*(1+IF(Settings!$B$11="Y",0,Settings!$B$10/100))+N(Settings!$B$9),"") | W79: =IF(ISNUMBER(V79),IF(V79*Settings!$B$8>1000,"beyond table",IFERROR(LOOKUP(V79*Settings!$B$8,'FOIS 145A'!$A$2:$A$22,'FOIS 145A'!$C$2:$C$22)*(1+IF(Settings!$B$11="Y",0,Settings!$B$10/100)),"")),"") | X79: =IF(AND(ISNUMBER(U79),ISNUMBER(W79)),U79+W79,"") | Y79: =Settings!$B$6
A80: Unknown | B80: no location in title | H80: 18308880 | I80: 2026_NTPC_112039_1 | J80: loading and transportation of 1,93,000 mt coal through rcr mode from - loading and transportation of 1,93,000 mt coal through rcr mode fromccl-chandragupta mines to nearby siding | K80: Coal transport (RCR / siding) | L80: National Thermal Power Corporation Limited | M80: Chhattisgarh | N80: Raipur | O80: 46289 | P80: AOC | Q80: Sarneshwar Transport And Construction Private Limited | R80: Bharat Road Carrier, Godavari Commodities, Nkas Services, Sangita Sales | S80: 5 named / 9 | T80: 9.26 | U80: =IF(ISNUMBER(G80),MAX(MAX(G80,Settings!$B$13)*Settings!$B$7*Settings!$B$5,IF(ISNUMBER(Settings!$B$12),Settings!$B$12,0))*(1+IF(Settings!$B$11="Y",0,Settings!$B$10/100))+N(Settings!$B$9),"") | W80: =IF(ISNUMBER(V80),IF(V80*Settings!$B$8>1000,"beyond table",IFERROR(LOOKUP(V80*Settings!$B$8,'FOIS 145A'!$A$2:$A$22,'FOIS 145A'!$C$2:$C$22)*(1+IF(Settings!$B$11="Y",0,Settings!$B$10/100)),"")),"") | X80: =IF(AND(ISNUMBER(U80),ISNUMBER(W80)),U80+W80,"") | Y80: =Settings!$B$6
A81: No | B81: mine named in title; plant/siding named in title | C81: Talcher / Angul | D81: 217 | E81: Talcher / Angul | F81: 217 | G81: 217 | H81: 18294456 | I81: 2026_NTPC_111977_1 | J81: transportation of 200000 mt coal from mcl talcher area mines to ntpc - transportation of 200000 mt coal from mcl talcher area mines to ntpcsimhadri super thermal power station under rcr mode | K81: Coal transport (RCR / siding) | L81: National Thermal Power Corporation Limited | M81: Chhattisgarh | N81: Raipur | O81: 46288 | P81: AOC | Q81: Bharat Road Carrier Private Limited | R81: Bharat Road Carrier, Sendoz Impex | S81: 3 named / 3 | T81: 8.2 | U81: =IF(ISNUMBER(G81),MAX(MAX(G81,Settings!$B$13)*Settings!$B$7*Settings!$B$5,IF(ISNUMBER(Settings!$B$12),Settings!$B$12,0))*(1+IF(Settings!$B$11="Y",0,Settings!$B$10/100))+N(Settings!$B$9),"") | W81: =IF(ISNUMBER(V81),IF(V81*Settings!$B$8>1000,"beyond table",IFERROR(LOOKUP(V81*Settings!$B$8,'FOIS 145A'!$A$2:$A$22,'FOIS 145A'!$C$2:$C$22)*(1+IF(Settings!$B$11="Y",0,Settings!$B$10/100)),"")),"") | X81: =IF(AND(ISNUMBER(U81),ISNUMBER(W81)),U81+W81,"") | Y81: =Settings!$B$6
A82: No | B82: mine named in title; plant/siding named in title | C82: Talcher / Angul | D82: 217 | E82: Talcher / Angul | F82: 217 | G82: 217 | H82: 17750799 | I82: GEM/2026/B/7536884 | J82: transportation of coal from coal mines in talcher area to nalco, damanjodi (nlod) alumina plant through road cum rail (rcr) mode | K82: Coal transport (RCR / siding) | L82: National Aluminium Company Limited | M82: Orissa | N82: Koraput | O82: 46184 | P82: AOC | Q82: Godavari Commodities Limited | R82: Godavari Commodities, Nkas Services | S82: 5 named / 10 | T82: 6.67 | U82: =IF(ISNUMBER(G82),MAX(MAX(G82,Settings!$B$13)*Settings!$B$7*Settings!$B$5,IF(ISNUMBER(Settings!$B$12),Settings!$B$12,0))*(1+IF(Settings!$B$11="Y",0,Settings!$B$10/100))+N(Settings!$B$9),"") | W82: =IF(ISNUMBER(V82),IF(V82*Settings!$B$8>1000,"beyond table",IFERROR(LOOKUP(V82*Settings!$B$8,'FOIS 145A'!$A$2:$A$22,'FOIS 145A'!$C$2:$C$22)*(1+IF(Settings!$B$11="Y",0,Settings!$B$10/100)),"")),"") | X82: =IF(AND(ISNUMBER(U82),ISNUMBER(W82)),U82+W82,"") | Y82: =Settings!$B$6
A83: No | B83: plant/siding named in title | E83: Talcher / Angul | F83: 217 | G83: 217 | H83: 17000112 | I83: GEM/2026/B/7393495 | J83: 2 lmt coal transportation from coal mines to alumina refinery plant, nalco, damanjodi, through road cum rail (rcr) mode | K83: Coal transport (RCR / siding) | L83: National Aluminium Company Limited | M83: Orissa | N83: Koraput | O83: 46122 | P83: AOC | Q83: Pragati Indian Road Lines | R83: Anoop Road Carriers, Sendoz Impex | S83: 5 named / 6 | T83: 2.44 | U83: =IF(ISNUMBER(G83),MAX(MAX(G83,Settings!$B$13)*Settings!$B$7*Settings!$B$5,IF(ISNUMBER(Settings!$B$12),Settings!$B$12,0))*(1+IF(Settings!$B$11="Y",0,Settings!$B$10/100))+N(Settings!$B$9),"") | W83: =IF(ISNUMBER(V83),IF(V83*Settings!$B$8>1000,"beyond table",IFERROR(LOOKUP(V83*Settings!$B$8,'FOIS 145A'!$A$2:$A$22,'FOIS 145A'!$C$2:$C$22)*(1+IF(Settings!$B$11="Y",0,Settings!$B$10/100)),"")),"") | X83: =IF(AND(ISNUMBER(U83),ISNUMBER(W83)),U83+W83,"") | Y83: =Settings!$B$6
A84: No | B84: mine named in title; plant/siding named in title | C84: Talcher / Angul | D84: 217 | E84: Talcher / Angul | F84: 217 | G84: 217 | H84: 13711181 | I84: GEM/2025/B/6166025 | J84: transportation of coal by road from mcl, talcher coalfield to cpp, nalco, angul including handling of coal and other related services | K84: Coal transport (road) | L84: National Aluminium Company Limited | M84: Orissa | N84: Angul | O84: 45803 | P84: AOC | Q84: Mukesh And Yogesh Roadlines | S84: 5 named / 10 | T84: 30.4 | U84: =IF(ISNUMBER(G84),MAX(MAX(G84,Settings!$B$13)*Settings!$B$7*Settings!$B$5,IF(ISNUMBER(Settings!$B$12),Settings!$B$12,0))*(1+IF(Settings!$B$11="Y",0,Settings!$B$10/100))+N(Settings!$B$9),"") | W84: =IF(ISNUMBER(V84),IF(V84*Settings!$B$8>1000,"beyond table",IFERROR(LOOKUP(V84*Settings!$B$8,'FOIS 145A'!$A$2:$A$22,'FOIS 145A'!$C$2:$C$22)*(1+IF(Settings!$B$11="Y",0,Settings!$B$10/100)),"")),"") | X84: =IF(AND(ISNUMBER(U84),ISNUMBER(W84)),U84+W84,"") | Y84: =Settings!$B$6
A85: No | B85: mine = coal company's tender city; siding = same area | C85: Talcher / Angul (tender city) | D85: 217 | E85: Talcher / Angul (tender city) | F85: 217 | G85: 217 | H85: 13504719 | I85: GEM/2025/B/6131875 | J85: loading and transportation | K85: Coal transport (road) | L85: Mahanadi Coalfields Limited | M85: Orissa | N85: Angul | O85: 45785 | P85: AOC | Q85: Hari Ram Godara | S85: 5 named / 13 | T85: 472.31 | U85: =IF(ISNUMBER(G85),MAX(MAX(G85,Settings!$B$13)*Settings!$B$7*Settings!$B$5,IF(ISNUMBER(Settings!$B$12),Settings!$B$12,0))*(1+IF(Settings!$B$11="Y",0,Settings!$B$10/100))+N(Settings!$B$9),"") | W85: =IF(ISNUMBER(V85),IF(V85*Settings!$B$8>1000,"beyond table",IFERROR(LOOKUP(V85*Settings!$B$8,'FOIS 145A'!$A$2:$A$22,'FOIS 145A'!$C$2:$C$22)*(1+IF(Settings!$B$11="Y",0,Settings!$B$10/100)),"")),"") | X85: =IF(AND(ISNUMBER(U85),ISNUMBER(W85)),U85+W85,"") | Y85: =Settings!$B$6
A86: No | B86: mine = coal company's tender city; siding = same area | C86: Talcher / Angul (tender city) | D86: 217 | E86: Talcher / Angul (tender city) | F86: 217 | G86: 217 | H86: 12563385 | I86: GEM/2025/B/5825045 | J86: loading and transportation | K86: Coal transport (road) | L86: Mahanadi Coalfields Limited | M86: Orissa | N86: Talcher | O86: 45691 | P86: AOC | Q86: Firstmove Logistics Private Limited | R86: Caliber Mining and Logistics | S86: 5 named / 13 | T86: 182.62 | U86: =IF(ISNUMBER(G86),MAX(MAX(G86,Settings!$B$13)*Settings!$B$7*Settings!$B$5,IF(ISNUMBER(Settings!$B$12),Settings!$B$12,0))*(1+IF(Settings!$B$11="Y",0,Settings!$B$10/100))+N(Settings!$B$9),"") | W86: =IF(ISNUMBER(V86),IF(V86*Settings!$B$8>1000,"beyond table",IFERROR(LOOKUP(V86*Settings!$B$8,'FOIS 145A'!$A$2:$A$22,'FOIS 145A'!$C$2:$C$22)*(1+IF(Settings!$B$11="Y",0,Settings!$B$10/100)),"")),"") | X86: =IF(AND(ISNUMBER(U86),ISNUMBER(W86)),U86+W86,"") | Y86: =Settings!$B$6
A87: No | B87: mine named in title; plant/siding named in title | C87: Talcher / Angul | D87: 217 | E87: Talcher / Angul | F87: 217 | G87: 217 | H87: 12422007 | I87: GEM/2024/B/5737749 | J87: transportation of coal by road from mcl talcher coalfield to cpp nalco an | K87: Coal transport (road) | L87: National Aluminium Company Limited | M87: Orissa | N87: Angul | O87: 45671 | P87: AOC | Q87: Omm Shakti Traders | S87: 5 named / 11 | T87: 8.07 | U87: =IF(ISNUMBER(G87),MAX(MAX(G87,Settings!$B$13)*Settings!$B$7*Settings!$B$5,IF(ISNUMBER(Settings!$B$12),Settings!$B$12,0))*(1+IF(Settings!$B$11="Y",0,Settings!$B$10/100))+N(Settings!$B$9),"") | W87: =IF(ISNUMBER(V87),IF(V87*Settings!$B$8>1000,"beyond table",IFERROR(LOOKUP(V87*Settings!$B$8,'FOIS 145A'!$A$2:$A$22,'FOIS 145A'!$C$2:$C$22)*(1+IF(Settings!$B$11="Y",0,Settings!$B$10/100)),"")),"") | X87: =IF(AND(ISNUMBER(U87),ISNUMBER(W87)),U87+W87,"") | Y87: =Settings!$B$6
A88: No | B88: plant/siding named in title | E88: Talcher / Angul | F88: 217 | G88: 217 | H88: 16901865 | I88: GEM/2026/B/7249129 | J88: loading supervision jobs of boiler coal supplies from coal companies, mcl, ecl and other cil subsidiaries to vsps , custom bid for services - minor repair of box wagons at mcl, talcher | K88: Loading / handling / crushing | L88: Rashtriya Ispat Nigam Limited | M88: Andhra Pradesh | N88: Visakhapatnam | O88: 46084 | P88: AOC | Q88: Ganga Logistics | R88: Godavari Commodities | S88: 5 named / 7 | T88: 1.01 | U88: =IF(ISNUMBER(G88),MAX(MAX(G88,Settings!$B$13)*Settings!$B$7*Settings!$B$5,IF(ISNUMBER(Settings!$B$12),Settings!$B$12,0))*(1+IF(Settings!$B$11="Y",0,Settings!$B$10/100))+N(Settings!$B$9),"") | W88: =IF(ISNUMBER(V88),IF(V88*Settings!$B$8>1000,"beyond table",IFERROR(LOOKUP(V88*Settings!$B$8,'FOIS 145A'!$A$2:$A$22,'FOIS 145A'!$C$2:$C$22)*(1+IF(Settings!$B$11="Y",0,Settings!$B$10/100)),"")),"") | X88: =IF(AND(ISNUMBER(U88),ISNUMBER(W88)),U88+W88,"") | Y88: =Settings!$B$6
A89: No | B89: mine = coal company's tender city; siding = same area | C89: Talcher / Angul (tender city) | D89: 217 | E89: Talcher / Angul (tender city) | F89: 217 | G89: 217 | H89: 12438622 | I89: GEM/2025/B/5775726 | J89: coal loading at pit head s | K89: Loading / handling / crushing | L89: Mahanadi Coalfields Limited | M89: Orissa | N89: Angul | O89: 45677 | P89: AOC | Q89: Saikrupa Transport | R89: Saikrupa Coal Supplier | S89: 5 named / 5 | T89: 25 | U89: =IF(ISNUMBER(G89),MAX(MAX(G89,Settings!$B$13)*Settings!$B$7*Settings!$B$5,IF(ISNUMBER(Settings!$B$12),Settings!$B$12,0))*(1+IF(Settings!$B$11="Y",0,Settings!$B$10/100))+N(Settings!$B$9),"") | W89: =IF(ISNUMBER(V89),IF(V89*Settings!$B$8>1000,"beyond table",IFERROR(LOOKUP(V89*Settings!$B$8,'FOIS 145A'!$A$2:$A$22,'FOIS 145A'!$C$2:$C$22)*(1+IF(Settings!$B$11="Y",0,Settings!$B$10/100)),"")),"") | X89: =IF(AND(ISNUMBER(U89),ISNUMBER(W89)),U89+W89,"") | Y89: =Settings!$B$6
A90: No | B90: mine = coal company's tender city; siding = same area | C90: Talcher / Angul (tender city) | D90: 217 | E90: Talcher / Angul (tender city) | F90: 217 | G90: 217 | H90: 16862563 | I90: GEM/2025/B/7048687 | J90: coal extraction kaniha ocp mcl | K90: Mining services (OB / extraction) | L90: Mahanadi Coalfields Limited | M90: Orissa | N90: Angul | O90: 46041 | P90: AOC | Q90: Vfpl Asipl Jv Company | S90: 5 named / 12 | T90: 117.55 | U90: =IF(ISNUMBER(G90),MAX(MAX(G90,Settings!$B$13)*Settings!$B$7*Settings!$B$5,IF(ISNUMBER(Settings!$B$12),Settings!$B$12,0))*(1+IF(Settings!$B$11="Y",0,Settings!$B$10/100))+N(Settings!$B$9),"") | W90: =IF(ISNUMBER(V90),IF(V90*Settings!$B$8>1000,"beyond table",IFERROR(LOOKUP(V90*Settings!$B$8,'FOIS 145A'!$A$2:$A$22,'FOIS 145A'!$C$2:$C$22)*(1+IF(Settings!$B$11="Y",0,Settings!$B$10/100)),"")),"") | X90: =IF(AND(ISNUMBER(U90),ISNUMBER(W90)),U90+W90,"") | Y90: =Settings!$B$6
A91: No | B91: plant = tender city in Telangana; named mine/plant is far | H91: 18305850 | I91: GEM/2026/B/7977472 | J91: supply of - domestic coal for ntpc (q3) - | quantity - 500000 | K91: Coal supply | L91: National Thermal Power Corporation Limited | M91: Telangana | N91: Karimnagar | O91: 46283 | P91: Financial | Q91: - | R91: Godavari Commodities | S91: 5 named / 11 | U91: =IF(ISNUMBER(G91),MAX(MAX(G91,Settings!$B$13)*Settings!$B$7*Settings!$B$5,IF(ISNUMBER(Settings!$B$12),Settings!$B$12,0))*(1+IF(Settings!$B$11="Y",0,Settings!$B$10/100))+N(Settings!$B$9),"") | W91: =IF(ISNUMBER(V91),IF(V91*Settings!$B$8>1000,"beyond table",IFERROR(LOOKUP(V91*Settings!$B$8,'FOIS 145A'!$A$2:$A$22,'FOIS 145A'!$C$2:$C$22)*(1+IF(Settings!$B$11="Y",0,Settings!$B$10/100)),"")),"") | X91: =IF(AND(ISNUMBER(U91),ISNUMBER(W91)),U91+W91,"") | Y91: =Settings!$B$6
A92: No | B92: plant = tender city in Andhra Pradesh; named mine/plant is far | H92: 18354395 | I92: GEM/2026/B/7977995 | J92: supply of - domestic coal for ntpc (q3) - | quantity - 500000 | K92: Coal supply | L92: National Thermal Power Corporation Limited | M92: Andhra Pradesh | N92: Visakhapatnam | O92: 46283 | P92: Financial | Q92: - | R92: Godavari Commodities | S92: 5 named / 11 | U92: =IF(ISNUMBER(G92),MAX(MAX(G92,Settings!$B$13)*Settings!$B$7*Settings!$B$5,IF(ISNUMBER(Settings!$B$12),Settings!$B$12,0))*(1+IF(Settings!$B$11="Y",0,Settings!$B$10/100))+N(Settings!$B$9),"") | W92: =IF(ISNUMBER(V92),IF(V92*Settings!$B$8>1000,"beyond table",IFERROR(LOOKUP(V92*Settings!$B$8,'FOIS 145A'!$A$2:$A$22,'FOIS 145A'!$C$2:$C$22)*(1+IF(Settings!$B$11="Y",0,Settings!$B$10/100)),"")),"") | X92: =IF(AND(ISNUMBER(U92),ISNUMBER(W92)),U92+W92,"") | Y92: =Settings!$B$6
A93: No | B93: plant = tender city in Maharashtra; named mine/plant is far | H93: 18382590 | I93: GEM/2026/B/7977546 | J93: supply of - domestic coal for ntpc (q3) - | quantity - 500000 | K93: Coal supply | L93: National Thermal Power Corporation Limited | M93: Maharashtra | N93: Nagpur | O93: 46283 | P93: Financial | Q93: - | R93: Godavari Commodities | S93: 5 named / 13 | U93: =IF(ISNUMBER(G93),MAX(MAX(G93,Settings!$B$13)*Settings!$B$7*Settings!$B$5,IF(ISNUMBER(Settings!$B$12),Settings!$B$12,0))*(1+IF(Settings!$B$11="Y",0,Settings!$B$10/100))+N(Settings!$B$9),"") | W93: =IF(ISNUMBER(V93),IF(V93*Settings!$B$8>1000,"beyond table",IFERROR(LOOKUP(V93*Settings!$B$8,'FOIS 145A'!$A$2:$A$22,'FOIS 145A'!$C$2:$C$22)*(1+IF(Settings!$B$11="Y",0,Settings!$B$10/100)),"")),"") | X93: =IF(AND(ISNUMBER(U93),ISNUMBER(W93)),U93+W93,"") | Y93: =Settings!$B$6
A94: No | B94: plant = tender city in Uttar Pradesh; named mine/plant is far | H94: 18400873 | I94: GEM/2026/B/7978009 | J94: supply of - domestic coal for ntpc (q3) - | quantity - 500000 | K94: Coal supply | L94: National Thermal Power Corporation Limited | M94: Uttar Pradesh | N94: Ambedkar Nagar | O94: 46283 | P94: Financial | Q94: - | R94: Godavari Commodities, Indermani / Indramani | S94: 5 named / 12 | U94: =IF(ISNUMBER(G94),MAX(MAX(G94,Settings!$B$13)*Settings!$B$7*Settings!$B$5,IF(ISNUMBER(Settings!$B$12),Settings!$B$12,0))*(1+IF(Settings!$B$11="Y",0,Settings!$B$10/100))+N(Settings!$B$9),"") | W94: =IF(ISNUMBER(V94),IF(V94*Settings!$B$8>1000,"beyond table",IFERROR(LOOKUP(V94*Settings!$B$8,'FOIS 145A'!$A$2:$A$22,'FOIS 145A'!$C$2:$C$22)*(1+IF(Settings!$B$11="Y",0,Settings!$B$10/100)),"")),"") | X94: =IF(AND(ISNUMBER(U94),ISNUMBER(W94)),U94+W94,"") | Y94: =Settings!$B$6
A95: No | B95: plant = tender city in Uttar Pradesh; named mine/plant is far | H95: 18214123 | I95: GEM/2026/B/7998022 | J95: supply of - domestic coal for ntpc (q3) - | quantity - 500000 | K95: Coal supply | L95: National Thermal Power Corporation Limited | M95: Uttar Pradesh | N95: Gautam Budhnagar | O95: 46274 | P95: AOC | Q95: Mohit Minerals Limited | R95: Godavari Commodities, Mohit Minerals, Sangita Sales | S95: 5 named / 8 | T95: 297.55 | U95: =IF(ISNUMBER(G95),MAX(MAX(G95,Settings!$B$13)*Settings!$B$7*Settings!$B$5,IF(ISNUMBER(Settings!$B$12),Settings!$B$12,0))*(1+IF(Settings!$B$11="Y",0,Settings!$B$10/100))+N(Settings!$B$9),"") | W95: =IF(ISNUMBER(V95),IF(V95*Settings!$B$8>1000,"beyond table",IFERROR(LOOKUP(V95*Settings!$B$8,'FOIS 145A'!$A$2:$A$22,'FOIS 145A'!$C$2:$C$22)*(1+IF(Settings!$B$11="Y",0,Settings!$B$10/100)),"")),"") | X95: =IF(AND(ISNUMBER(U95),ISNUMBER(W95)),U95+W95,"") | Y95: =Settings!$B$6
A96: No | B96: plant = tender city in Bihar; named mine/plant is far | H96: 18261397 | I96: GEM/2026/B/7997430 | J96: supply of - domestic coal for ntpc (q3) - | quantity - 500000 | K96: Coal supply | L96: National Thermal Power Corporation Limited | M96: Bihar | N96: Patna | O96: 46274 | P96: AOC | Q96: Shri Harjika Enterprises | R96: Godavari Commodities, Mohit Minerals, Sangita Sales | S96: 5 named / 8 | T96: 255.98 | U96: =IF(ISNUMBER(G96),MAX(MAX(G96,Settings!$B$13)*Settings!$B$7*Settings!$B$5,IF(ISNUMBER(Settings!$B$12),Settings!$B$12,0))*(1+IF(Settings!$B$11="Y",0,Settings!$B$10/100))+N(Settings!$B$9),"") | W96: =IF(ISNUMBER(V96),IF(V96*Settings!$B$8>1000,"beyond table",IFERROR(LOOKUP(V96*Settings!$B$8,'FOIS 145A'!$A$2:$A$22,'FOIS 145A'!$C$2:$C$22)*(1+IF(Settings!$B$11="Y",0,Settings!$B$10/100)),"")),"") | X96: =IF(AND(ISNUMBER(U96),ISNUMBER(W96)),U96+W96,"") | Y96: =Settings!$B$6
A97: No | B97: plant = tender city in Uttar Pradesh; named mine/plant is far | H97: 18214127 | I97: GEM/2026/B/7997400 | J97: supply of - domestic coal for ntpc (q3) - | quantity - 500000 | K97: Coal supply | L97: National Thermal Power Corporation Limited | M97: Uttar Pradesh | N97: Raebareli | O97: 46274 | P97: Financial | Q97: - | R97: Godavari Commodities, Indermani / Indramani, Mohit Minerals, Sangita Sales | S97: 5 named / 9 | U97: =IF(ISNUMBER(G97),MAX(MAX(G97,Settings!$B$13)*Settings!$B$7*Settings!$B$5,IF(ISNUMBER(Settings!$B$12),Settings!$B$12,0))*(1+IF(Settings!$B$11="Y",0,Settings!$B$10/100))+N(Settings!$B$9),"") | W97: =IF(ISNUMBER(V97),IF(V97*Settings!$B$8>1000,"beyond table",IFERROR(LOOKUP(V97*Settings!$B$8,'FOIS 145A'!$A$2:$A$22,'FOIS 145A'!$C$2:$C$22)*(1+IF(Settings!$B$11="Y",0,Settings!$B$10/100)),"")),"") | X97: =IF(AND(ISNUMBER(U97),ISNUMBER(W97)),U97+W97,"") | Y97: =Settings!$B$6
A98: No | B98: plant = tender city in Tamil Nadu; named mine/plant is far | H98: 18065871 | I98: 2026_TNPL_694205_1 | J98: procurement of 4200 gar imported steaming non coking coal in bulk | K98: Coal supply | L98: Tamil Nadu Newsprint And Papers Limited | M98: Tamil Nadu | N98: Karur | O98: 46262 | P98: AOC | Q98: Smartgen Infra Private Limited | R98: Mohit Minerals | S98: 5 named / 6 | T98: 128.57 | U98: =IF(ISNUMBER(G98),MAX(MAX(G98,Settings!$B$13)*Settings!$B$7*Settings!$B$5,IF(ISNUMBER(Settings!$B$12),Settings!$B$12,0))*(1+IF(Settings!$B$11="Y",0,Settings!$B$10/100))+N(Settings!$B$9),"") | W98: =IF(ISNUMBER(V98),IF(V98*Settings!$B$8>1000,"beyond table",IFERROR(LOOKUP(V98*Settings!$B$8,'FOIS 145A'!$A$2:$A$22,'FOIS 145A'!$C$2:$C$22)*(1+IF(Settings!$B$11="Y",0,Settings!$B$10/100)),"")),"") | X98: =IF(AND(ISNUMBER(U98),ISNUMBER(W98)),U98+W98,"") | Y98: =Settings!$B$6
A99: No | B99: plant = tender city in Madhya Pradesh; named mine/plant is far | H99: 18318773 | I99: GEM/2026/B/7657978 | J99: supply of - coal - | quantity - 24000 | K99: Coal supply | L99: Bharat Petroleum Corporation Limited | M99: Madhya Pradesh | N99: Sagar | O99: 46213 | P99: Financial | Q99: - | R99: Godavari Commodities | S99: 5 named / 15 | U99: =IF(ISNUMBER(G99),MAX(MAX(G99,Settings!$B$13)*Settings!$B$7*Settings!$B$5,IF(ISNUMBER(Settings!$B$12),Settings!$B$12,0))*(1+IF(Settings!$B$11="Y",0,Settings!$B$10/100))+N(Settings!$B$9),"") | W99: =IF(ISNUMBER(V99),IF(V99*Settings!$B$8>1000,"beyond table",IFERROR(LOOKUP(V99*Settings!$B$8,'FOIS 145A'!$A$2:$A$22,'FOIS 145A'!$C$2:$C$22)*(1+IF(Settings!$B$11="Y",0,Settings!$B$10/100)),"")),"") | X99: =IF(AND(ISNUMBER(U99),ISNUMBER(W99)),U99+W99,"") | Y99: =Settings!$B$6
A100: No | B100: plant = tender city in Madhya Pradesh; named mine/plant is far | H100: 17929382 | I100: GEM/2026/B/7629446 | J100: supply of - domestic coal for ntpc (q3) - | quantity - 500000 | K100: Coal supply | L100: National Thermal Power Corporation Limited | M100: Madhya Pradesh | N100: Narsinghpur | O100: 46209 | P100: AOC | Q100: Shri Harjika Enterprises, Tirupati Minerals Private Limited | R100: Godavari Commodities, Indermani / Indramani | S100: 5 named / 11 | T100: 245.72 | U100: =IF(ISNUMBER(G100),MAX(MAX(G100,Settings!$B$13)*Settings!$B$7*Settings!$B$5,IF(ISNUMBER(Settings!$B$12),Settings!$B$12,0))*(1+IF(Settings!$B$11="Y",0,Settings!$B$10/100))+N(Settings!$B$9),"") | W100: =IF(ISNUMBER(V100),IF(V100*Settings!$B$8>1000,"beyond table",IFERROR(LOOKUP(V100*Settings!$B$8,'FOIS 145A'!$A$2:$A$22,'FOIS 145A'!$C$2:$C$22)*(1+IF(Settings!$B$11="Y",0,Settings!$B$10/100)),"")),"") | X100: =IF(AND(ISNUMBER(U100),ISNUMBER(W100)),U100+W100,"") | Y100: =Settings!$B$6
...

Sheet Edge summary
A1: Category | B1: Edge: Yes | C1: Borderline | D1: Unknown | E1: No | F1: Edge Yes awarded Rs Cr (sum)
A2: Coal supply | B2: =COUNTIFS(Master!$K$2:$K$321,$A2,Master!$A$2:$A$321,"Yes") | C2: =COUNTIFS(Master!$K$2:$K$321,$A2,Master!$A$2:$A$321,"Borderline") | D2: =COUNTIFS(Master!$K$2:$K$321,$A2,Master!$A$2:$A$321,"Unknown") | E2: =COUNTIFS(Master!$K$2:$K$321,$A2,Master!$A$2:$A$321,"No") | F2: =SUMIFS(Master!$T$2:$T$321,Master!$K$2:$K$321,$A2,Master!$A$2:$A$321,"Yes")
A3: Coal transport (RCR / siding) | B3: =COUNTIFS(Master!$K$2:$K$321,$A3,Master!$A$2:$A$321,"Yes") | C3: =COUNTIFS(Master!$K$2:$K$321,$A3,Master!$A$2:$A$321,"Borderline") | D3: =COUNTIFS(Master!$K$2:$K$321,$A3,Master!$A$2:$A$321,"Unknown") | E3: =COUNTIFS(Master!$K$2:$K$321,$A3,Master!$A$2:$A$321,"No") | F3: =SUMIFS(Master!$T$2:$T$321,Master!$K$2:$K$321,$A3,Master!$A$2:$A$321,"Yes")
A4: Coal transport (road) | B4: =COUNTIFS(Master!$K$2:$K$321,$A4,Master!$A$2:$A$321,"Yes") | C4: =COUNTIFS(Master!$K$2:$K$321,$A4,Master!$A$2:$A$321,"Borderline") | D4: =COUNTIFS(Master!$K$2:$K$321,$A4,Master!$A$2:$A$321,"Unknown") | E4: =COUNTIFS(Master!$K$2:$K$321,$A4,Master!$A$2:$A$321,"No") | F4: =SUMIFS(Master!$T$2:$T$321,Master!$K$2:$K$321,$A4,Master!$A$2:$A$321,"Yes")
A5: Loading / handling / crushing | B5: =COUNTIFS(Master!$K$2:$K$321,$A5,Master!$A$2:$A$321,"Yes") | C5: =COUNTIFS(Master!$K$2:$K$321,$A5,Master!$A$2:$A$321,"Borderline") | D5: =COUNTIFS(Master!$K$2:$K$321,$A5,Master!$A$2:$A$321,"Unknown") | E5: =COUNTIFS(Master!$K$2:$K$321,$A5,Master!$A$2:$A$321,"No") | F5: =SUMIFS(Master!$T$2:$T$321,Master!$K$2:$K$321,$A5,Master!$A$2:$A$321,"Yes")
A6: Mining services (OB / extraction) | B6: =COUNTIFS(Master!$K$2:$K$321,$A6,Master!$A$2:$A$321,"Yes") | C6: =COUNTIFS(Master!$K$2:$K$321,$A6,Master!$A$2:$A$321,"Borderline") | D6: =COUNTIFS(Master!$K$2:$K$321,$A6,Master!$A$2:$A$321,"Unknown") | E6: =COUNTIFS(Master!$K$2:$K$321,$A6,Master!$A$2:$A$321,"No") | F6: =SUMIFS(Master!$T$2:$T$321,Master!$K$2:$K$321,$A6,Master!$A$2:$A$321,"Yes")
A7: Other | B7: =COUNTIFS(Master!$K$2:$K$321,$A7,Master!$A$2:$A$321,"Yes") | C7: =COUNTIFS(Master!$K$2:$K$321,$A7,Master!$A$2:$A$321,"Borderline") | D7: =COUNTIFS(Master!$K$2:$K$321,$A7,Master!$A$2:$A$321,"Unknown") | E7: =COUNTIFS(Master!$K$2:$K$321,$A7,Master!$A$2:$A$321,"No") | F7: =SUMIFS(Master!$T$2:$T$321,Master!$K$2:$K$321,$A7,Master!$A$2:$A$321,"Yes")
A8: Other (biomass / coke) | B8: =COUNTIFS(Master!$K$2:$K$321,$A8,Master!$A$2:$A$321,"Yes") | C8: =COUNTIFS(Master!$K$2:$K$321,$A8,Master!$A$2:$A$321,"Borderline") | D8: =COUNTIFS(Master!$K$2:$K$321,$A8,Master!$A$2:$A$321,"Unknown") | E8: =COUNTIFS(Master!$K$2:$K$321,$A8,Master!$A$2:$A$321,"No") | F8: =SUMIFS(Master!$T$2:$T$321,Master!$K$2:$K$321,$A8,Master!$A$2:$A$321,"Yes")
A9: Washery / beneficiation | B9: =COUNTIFS(Master!$K$2:$K$321,$A9,Master!$A$2:$A$321,"Yes") | C9: =COUNTIFS(Master!$K$2:$K$321,$A9,Master!$A$2:$A$321,"Borderline") | D9: =COUNTIFS(Master!$K$2:$K$321,$A9,Master!$A$2:$A$321,"Unknown") | E9: =COUNTIFS(Master!$K$2:$K$321,$A9,Master!$A$2:$A$321,"No") | F9: =SUMIFS(Master!$T$2:$T$321,Master!$K$2:$K$321,$A9,Master!$A$2:$A$321,"Yes")
A10: Total | B10: =SUM(B2:B9) | C10: =SUM(C2:C9) | D10: =SUM(D2:D9) | E10: =SUM(E2:E9) | F10: =SUM(F2:F9)

Sheet Settings
A2: Setting | B2: Value | C2: Note
A3: Road rate Rs per tonne-km (YOUR NUMBER) | B3: 5 | C3: Aman, chat 2026-10-12: approx Rs 5 per tonne per km (approximate, not a written quote). Clear to use the illustrative rate.
A4: Illustrative road Rs per tonne-km | B4: 2.75 | C4: Indicative general-truck range Rs 2.0-3.5. NOT a coal quote.
A5: Road rate used | B5: =IF(ISNUMBER(B3),B3,B4)
A6: Rate status | B6: =IF(ISNUMBER(B3),"Your quote","ILLUSTRATIVE - replace with your quote")
A7: Road km = straight-line x | B7: 1.3 | C7: Typical road winding factor [UNVERIFIED].
A8: Rail km = straight-line x | B8: 1.2 | C8: Typical rail winding factor [UNVERIFIED]. FOIS charges on railway chargeable distance.
A9: Loading + unloading Rs per tonne (per handling) | C9: Blank counts as 0.
A10: GST on freight % | B10: 5 | C10: Per the FOIS calculator note.
A11: Take GST credit? (Y/N) | B11: N | C11: Y removes GST from the cost.
A12: Minimum road Rs per tonne | C12: Blank = no minimum.
A13: Minimum haul km | B13: 25 | C13: Floor for a same-town haul [UNVERIFIED].
A14: Edge radius km | B14: 150 | C14: Your rule: 150 km.
A15: Reference point | B15: Raigarh town (siding station not yet given) | C15: Give me your siding's railway station and I will re-run from it.

Sheet FOIS 145A
A1: From km | B1: To km | C1: Rs per tonne (base, train load)
A2: 1 | B2: 100 | C2: 216
A3: 101 | B3: 125 | C3: 389.6
A4: 126 | B4: 150 | C4: 448.9
A5: 151 | B5: 175 | C5: 488.7
A6: 176 | B6: 200 | C6: 532.2
A7: 201 | B7: 275 | C7: 672.5
A8: 276 | B8: 350 | C8: 797.2
A9: 351 | B9: 425 | C9: 926
A10: 426 | B10: 500 | C10: 1054.7
A11: 501 | B11: 600 | C11: 1228
A12: 601 | B12: 700 | C12: 1398.7
A13: 701 | B13: 730 | C13: 1435.6
... A22: 971 | B22: 1000 | C22: 1891.8
A24: FOIS rate class 145A train load, base tariff, read 2026-10-12

Sheet Competitors
A1: Group | B1: Competitor | C1: Tenders bid (export) | D1: Wins (export) | E1: Won Rs Cr (export) | F1: Wins in this sheet | G1: Wins on EDGE tenders (Yes) | H1: Edge tenders they won, Rs Cr
A2: User's 15 | B2: Godavari Commodities | C2: 60 | D2: 4 | E2: 282.37 | F2: =COUNTIF(Master!$Q$2:$Q$321,"*"&IFERROR(LEFT(B2,FIND(" /",B2)-1),B2)&"*") | G2: =COUNTIFS(Master!$Q$2:$Q$321,"*"&IFERROR(LEFT(B2,FIND(" /",B2)-1),B2)&"*",Master!$A$2:$A$321,"Yes") | H2: =SUMIFS(Master!$T$2:$T$321,Master!$Q$2:$Q$321,"*"&IFERROR(LEFT(B2,FIND(" /",B2)-1),B2)&"*",Master!$A$2:$A$321,"Yes")
A3: Other (recommended) | B3: G K Associates | C3: 40 | D3: 5 | E3: 374.77 | F3: =COUNTIF(Master!$Q$2:$Q$321,"*"&IFERROR(LEFT(B3,FIND(" /",B3)-1),B3)&"*") | G3: =COUNTIFS(Master!$Q$2:$Q$321,"*"&IFERROR(LEFT(B3,FIND(" /",B3)-1),B3)&"*",Master!$A$2:$A$321,"Yes") | H3: =SUMIFS(Master!$T$2:$T$321,Master!$Q$2:$Q$321,"*"&IFERROR(LEFT(B3,FIND(" /",B3)-1),B3)&"*",Master!$A$2:$A$321,"Yes")
A4: User's 15 | B4: Mohit Minerals | C4: 24 | D4: 5 | E4: 793.62 | F4: =COUNTIF(Master!$Q$2:$Q$321,"*"&IFERROR(LEFT(B4,FIND(" /",B4)-1),B4)&"*") | G4: =COUNTIFS(Master!$Q$2:$Q$321,"*"&IFERROR(LEFT(B4,FIND(" /",B4)-1),B4)&"*",Master!$A$2:$A$321,"Yes") | H4: =SUMIFS(Master!$T$2:$T$321,Master!$Q$2:$Q$321,"*"&IFERROR(LEFT(B4,FIND(" /",B4)-1),B4)&"*",Master!$A$2:$A$321,"Yes")
A5: User's 15 | B5: Anoop Road Carriers | C5: 19 | D5: 0 | E5: 0 | F5: =COUNTIF(Master!$Q$2:$Q$321,"*"&IFERROR(LEFT(B5,FIND(" /",B5)-1),B5)&"*") | G5: =COUNTIFS(Master!$Q$2:$Q$321,"*"&IFERROR(LEFT(B5,FIND(" /",B5)-1),B5)&"*",Master!$A$2:$A$321,"Yes") | H5: =SUMIFS(Master!$T$2:$T$321,Master!$Q$2:$Q$321,"*"&IFERROR(LEFT(B5,FIND(" /",B5)-1),B5)&"*",Master!$A$2:$A$321,"Yes")
A6: Other (recommended) | B6: Nkas Services | C6: 19 | D6: 0 | E6: 0 | F6: =COUNTIF(Master!$Q$2:$Q$321,"*"&IFERROR(LEFT(B6,FIND(" /",B6)-1),B6)&"*") | G6: =COUNTIFS(Master!$Q$2:$Q$321,"*"&IFERROR(LEFT(B6,FIND(" /",B6)-1),B6)&"*",Master!$A$2:$A$321,"Yes") | H6: =SUMIFS(Master!$T$2:$T$321,Master!$Q$2:$Q$321,"*"&IFERROR(LEFT(B6,FIND(" /",B6)-1),B6)&"*",Master!$A$2:$A$321,"Yes")
A7: Other (recommended) | B7: Chandan Kumar Singh | C7: 15 | D7: 4 | E7: 11.95 | F7: =COUNTIF(Master!$Q$2:$Q$321,"*"&IFERROR(LEFT(B7,FIND(" /",B7)-1),B7)&"*") | G7: =COUNTIFS(Master!$Q$2:$Q$321,"*"&IFERROR(LEFT(B7,FIND(" /",B7)-1),B7)&"*",Master!$A$2:$A$321,"Yes") | H7: =SUMIFS(Master!$T$2:$T$321,Master!$Q$2:$Q$321,"*"&IFERROR(LEFT(B7,FIND(" /",B7)-1),B7)&"*",Master!$A$2:$A$321,"Yes")
A8: Other (recommended) | B8: Sangita Sales | C8: 15 | D8: 1 | E8: 1.16 | F8: =COUNTIF(Master!$Q$2:$Q$321,"*"&IFERROR(LEFT(B8,FIND(" /",B8)-1),B8)&"*") | G8: =COUNTIFS(Master!$Q$2:$Q$321,"*"&IFERROR(LEFT(B8,FIND(" /",B8)-1),B8)&"*",Master!$A$2:$A$321,"Yes") | H8: =SUMIFS(Master!$T$2:$T$321,Master!$Q$2:$Q$321,"*"&IFERROR(LEFT(B8,FIND(" /",B8)-1),B8)&"*",Master!$A$2:$A$321,"Yes")
A9: Other (recommended) | B9: Bharat Road Carrier | C9: 14 | D9: 3 | E9: 16.67 | F9: =COUNTIF(Master!$Q$2:$Q$321,"*"&IFERROR(LEFT(B9,FIND(" /",B9)-1),B9)&"*") | G9: =COUNTIFS(Master!$Q$2:$Q$321,"*"&IFERROR(LEFT(B9,FIND(" /",B9)-1),B9)&"*",Master!$A$2:$A$321,"Yes") | H9: =SUMIFS(Master!$T$2:$T$321,Master!$Q$2:$Q$321,"*"&IFERROR(LEFT(B9,FIND(" /",B9)-1),B9)&"*",Master!$A$2:$A$321,"Yes")
A10: Other (recommended) | B10: Saikrupa Coal Supplier | C10: 14 | D10: 2 | E10: 34.97 | F10: =COUNTIF(Master!$Q$2:$Q$321,"*"&IFERROR(LEFT(B10,FIND(" /",B10)-1),B10)&"*") | G10: =COUNTIFS(Master!$Q$2:$Q$321,"*"&IFERROR(LEFT(B10,FIND(" /",B10)-1),B10)&"*",Master!$A$2:$A$321,"Yes") | H10: =SUMIFS(Master!$T$2:$T$321,Master!$Q$2:$Q$321,"*"&IFERROR(LEFT(B10,FIND(" /",B10)-1),B10)&"*",Master!$A$2:$A$321,"Yes")
A11: Tender247 shortlist | B11: United Coal Carriers | C11: 14 | D11: 4 | E11: 4.23 | F11: =COUNTIF(Master!$Q$2:$Q$321,"*"&IFERROR(LEFT(B11,FIND(" /",B11)-1),B11)&"*") | G11: =COUNTIFS(Master!$Q$2:$Q$321,"*"&IFERROR(LEFT(B11,FIND(" /",B11)-1),B11)&"*",Master!$A$2:$A$321,"Yes") | H11: =SUMIFS(Master!$T$2:$T$321,Master!$Q$2:$Q$321,"*"&IFERROR(LEFT(B11,FIND(" /",B11)-1),B11)&"*",Master!$A$2:$A$321,"Yes")
A12: User's 15 | B12: Indermani / Indramani | C12: 12 | D12: 2 | E12: 512.64 | F12: =COUNTIF(Master!$Q$2:$Q$321,"*"&IFERROR(LEFT(B12,FIND(" /",B12)-1),B12)&"*") | G12: =COUNTIFS(Master!$Q$2:$Q$321,"*"&IFERROR(LEFT(B12,FIND(" /",B12)-1),B12)&"*",Master!$A$2:$A$321,"Yes") | H12: =SUMIFS(Master!$T$2:$T$321,Master!$Q$2:$Q$321,"*"&IFERROR(LEFT(B12,FIND(" /",B12)-1),B12)&"*",Master!$A$2:$A$321,"Yes")
A13: Tender247 shortlist | B13: Caliber Mining and Logistics | C13: 8 | D13: 2 | E13: 2947.85 | F13: =COUNTIF(Master!$Q$2:$Q$321,"*"&IFERROR(LEFT(B13,FIND(" /",B13)-1),B13)&"*") | G13: =COUNTIFS(Master!$Q$2:$Q$321,"*"&IFERROR(LEFT(B13,FIND(" /",B13)-1),B13)&"*",Master!$A$2:$A$321,"Yes") | H13: =SUMIFS(Master!$T$2:$T$321,Master!$Q$2:$Q$321,"*"&IFERROR(LEFT(B13,FIND(" /",B13)-1),B13)&"*",Master!$A$2:$A$321,"Yes")
... A23: Tender247 shortlist | B23: Vedvyas Logistic | C23: 1 | D23: 0 | E23: 0 | F23: =COUNTIF(Master!$Q$2:$Q$321,"*"&IFERROR(LEFT(B23,FIND(" /",B23)-1),B23)&"*") | G23: =COUNTIFS(Master!$Q$2:$Q$321,"*"&IFERROR(LEFT(B23,FIND(" /",B23)-1),B23)&"*",Master!$A$2:$A$321,"Yes") | H23: =SUMIFS(Master!$T$2:$T$321,Master!$Q$2:$Q$321,"*"&IFERROR(LEFT(B23,FIND(" /",B23)-1),B23)&"*",Master!$A$2:$A$321,"Yes")
A25: Names match the Tender247 winner spelling; counts can differ from the export when spellings differ.
